Workbook

Sheet Raw Data
A1: Order_ID | B1: Order_Date | C1: City | D1: Cuisine | E1: Customer_Type | F1: Payment_Method | G1: Order_Value | H1: Discount | I1: Delivery_Fee | J1: Delivery_Time_Min | K1: Rating | L1: Order_Status
A2: FD100001 | B2: 45951 | C2: Hyderabad | D2: South Indian | E2: New | F2: Credit Card | G2: 309 | H2: 0 | I2: 30 | J2: 28 | K2: 3.5 | L2: Delivered
A3: FD100002 | B3: 45835 | C3: Ahmedabad | D3: Pizza | E3: Returning | F3: UPI | G3: 517 | H3: 0 | I3: 0 | J3: 24 | K3: 4.7 | L3: Delivered
A4: FD100003 | B4: 45978 | C4: Delhi | D4: Biryani | E4: Returning | F4: Credit Card | G4: 512 | H4: 0 | I4: 0 | J4: 31 | K4: 4.2 | L4: Delivered
A5: FD100004 | B5: 45926 | C5: Bengaluru | D5: Chinese | E5: Returning | F5: UPI | G5: 491 | H5: 64 | I5: 20 | J5: 51 | K5: 3.2 | L5: Delivered
A6: FD100005 | B6: 45699 | C6: Chennai | D6: North Indian | E6: New | F6: UPI | G6: 678 | H6: 0 | I6: 0 | J6: 31 | K6: 3.8 | L6: Delivered
A7: FD100006 | B7: 46015 | C7: Bengaluru | D7: Chinese | E7: Returning | F7: Credit Card | G7: 540 | H7: 0 | I7: 0 | J7: 38 | K7: 3.7 | L7: Delivered
A8: FD100007 | B8: 45947 | C8: Hyderabad | D8: Pizza | E8: Returning | F8: Debit Card | G8: 592 | H8: 0 | I8: 0 | J8: 34 | K8: 4.7 | L8: Delivered
A9: FD100008 | B9: 45955 | C9: Bengaluru | D9: North Indian | E9: New | F9: Cash on Delivery | G9: 546 | H9: 84 | I9: 0 | J9: 47 | K9: 4.6 | L9: Delivered
A10: FD100009 | B10: 45713 | C10: Delhi | D10: North Indian | E10: Returning | F10: Cash on Delivery | G10: 393 | H10: 68 | I10: 30 | J10: 34 | K10: 5 | L10: Delivered
A11: FD100010 | B11: 45839 | C11: Hyderabad | D11: Chinese | E11: New | F11: Cash on Delivery | G11: 525 | H11: 74 | I11: 0 | J11: 39 | K11: 3.4 | L11: Delivered
A12: FD100011 | B12: 45809 | C12: Mumbai | D12: Biryani | E12: Returning | G12: 412 | H12: 0 | I12: 20 | J12: 29 | K12: 3.7 | L12: Delivered
A13: FD100012 | B13: 46000 | C13: Mumbai | D13: South Indian | E13: Returning | F13: Cash on Delivery | G13: 421 | H13: 98 | I13: 45 | J13: 46 | K13: 3.3 | L13: Delivered
A14: FD100013 | B14: 45907 | C14: Hyderabad | D14: Chinese | E14: Returning | F14: UPI | G14: 430 | H14: 0 | I14: 20 | J14: 33 | K14: 5 | L14: Delivered
A15: FD100014 | B15: 45967 | C15: Hyderabad | D15: Chinese | E15: New | F15: Debit Card | G15: 268 | H15: 38 | I15: 20 | J15: 33 | K15: 4.5 | L15: Delivered
A16: FD100015 | B16: 45836 | C16: Pune | D16: Biryani | E16: New | F16: UPI | G16: 366 | H16: 40 | I16: 45 | J16: 25 | K16: 4.6 | L16: Delivered
A17: FD100016 | B17: 45754 | C17: Delhi | D17: Chinese | E17: New | F17: UPI | G17: 337 | H17: 41 | I17: 30 | J17: 27 | K17: 4.6 | L17: Delivered
A18: FD100017 | B18: 45877 | C18: Mumbai | D18: Healthy | E18: Returning | F18: UPI | G18: 379 | H18: 70 | I18: 40 | J18: 26 | K18: 4.5 | L18: Delivered
A19: FD100018 | B19: 45686 | C19: Kolkata | D19: North Indian | E19: New | F19: Cash on Delivery | G19: 540 | H19: 0 | I19: 0 | J19: 30 | K19: 3.8 | L19: Delivered
A20: FD100019 | B20: 45968 | C20: Mumbai | D20: Biryani | E20: Returning | F20: Cash on Delivery | G20: 566 | H20: 0 | I20: 0 | J20: 42 | K20: 4.4 | L20: Delivered
A21: FD100020 | B21: 45903 | C21: Mumbai | D21: Biryani | E21: New | F21: Wallet | G21: 315 | H21: 40 | I21: 30 | J21: 31 | K21: 4.3 | L21: Delivered
A22: FD100021 | B22: 45946 | C22: Delhi | D22: Fast Food | E22: New | F22: Wallet | G22: 315 | H22: 47 | I22: 30 | J22: 25 | K22: 3.9 | L22: Delivered
A23: FD100022 | B23: 45803 | C23: Bengaluru | D23: Chinese | E23: returning | F23: Wallet | G23: 358 | H23: 0 | I23: 45 | J23: 36 | K23: 4.5 | L23: Delivered
A24: FD100023 | B24: 46013 | C24: Pune | D24: Fast Food | E24: Returning | F24: UPI | G24: 220 | H24: 0 | I24: 40 | J24: 27 | K24: 4.3 | L24: Delivered
... A27: FD100026 | B27: 45741 | C27: Mumbai | D27: North Indian | E27: Returning | F27: Wallet | G27: 455 | H27: 70 | I27: 30 | J27: 45 | K27: 4.5 | L27: Delivered
A28: FD100027 | B28: 07-07-2025 | C28: Delhi | D28: Biryani | E28: Returning | F28: UPI | G28: 382 | H28: 46 | I28: 45 | J28: 45 | K28: 4.1 | L28: Delivered
A29: FD100028 | B29: 45677 | C29: Bengaluru | D29: South Indian | E29: Returning | F29: UPI | G29: 367 | H29: 0 | I29: 40 | L29: Cancelled
A30: FD100029 | B30: 45724 | C30: Mumbai | D30: Pizza | E30: New | F30: Wallet | G30: 617 | H30: 0 | I30: 0 | J30: 27 | K30: 4.6 | L30: Delivered
A31: FD100030 | B31: 45920 | C31: DELHI | D31: Fast Food | E31: Returning | F31: UPI | G31: 454 | H31: 0 | I31: 30 | L31: Cancelled
A32: FD100031 | B32: 45941 | C32: Delhi | D32: Chinese | E32: Returning | F32: UPI | G32: 374 | H32: 43 | I32: 40 | J32: 41 | K32: 4.4 | L32: Delivered
A33: FD100032 | B33: 46012 | C33: Mumbai | D33: North Indian | E33: New | F33: Credit Card | G33: 351 | H33: 67 | I33: 20 | J33: 35 | K33: 4.8 | L33: Delivered
A34: FD100033 | B34: 45793 | C34: Bengaluru | D34: Biryani | E34: Returning | F34: UPI | H34: 0 | I34: 20 | J34: 48 | K34: 3.6 | L34: Delivered
A35: FD100034 | B35: 45809 | C35: Hyderabad | D35: Biryani | E35: Returning | F35: UPI | G35: 518 | H35: 58 | I35: 0 | J35: 34 | K35: 4.6 | L35: Delivered
A36: FD100035 | B36: 45846 | C36: Mumbai | D36: Desserts | E36: Returning | F36: Wallet | G36: 417 | H36: 0 | I36: 40 | J36: 49 | K36: 3.1 | L36: Delivered
A37: FD100036 | B37: 45738 | C37: Bengaluru | D37: Chinese | E37: New | F37: Wallet | G37: 312 | H37: 0 | I37: 30 | J37: 49 | K37: 3.9 | L37: Delivered
A38: FD100037 | B38: 45714 | C38: Chennai | D38: Pizza | E38: Returning | F38: Wallet | G38: 750 | H38: 183 | I38: 0 | J38: 38 | K38: 4.1 | L38: Delivered
A39: FD100038 | B39: 45848 | C39: Hyderabad | D39: North Indian | E39: Returning | F39: UPI | G39: 508 | H39: 0 | I39: 0 | J39: 30 | K39: 5 | L39: Delivered
A40: FD100039 | B40: 45753 | C40: Chennai | D40: North Indian | E40: New | F40: UPI | G40: 475 | H40: 78 | I40: 30 | J40: 30 | L40: Delivered
A41: FD100040 | B41: 45916 | C41: Bengaluru | D41: Pizza | E41: Returning | F41: Credit Card | G41: 832 | H41: 0 | I41: 0 | J41: 40 | K41: 4.5 | L41: Delivered
A42: FD100041 | B42: 45834 | C42: Chennai | D42: Fast Food | E42: New | F42: Credit Card | G42: 416 | H42: 94 | I42: 40 | J42: 20 | K42: 3.8 | L42: Delivered
A43: FD100042 | B43: 45970 | C43: Delhi | D43: Healthy | E43: New | F43: UPI | G43: 356 | H43: 55 | I43: 40 | J43: 46 | K43: 3.8 | L43: Delivered
A44: FD100043 | B44: 45926 | C44: Delhi | D44: Chinese | E44: Returning | F44: Cash on Delivery | G44: 371 | H44: 46 | I44: 20 | J44: 41 | K44: 3.7 | L44: Delivered
A45: FD100044 | B45: 45787 | C45: Mumbai | D45: Fast Food | E45: Returning | F45: Wallet | G45: 409 | H45: 75 | I45: 30 | J45: 36 | K45: 5 | L45: Delivered
A46: FD100045 | B46: 45970 | C46: Bengaluru | D46: Chinese | E46: Returning | F46: Credit Card | G46: 342 | H46: 59 | I46: 20 | J46: 51 | K46: 3.5 | L46: Delivered
A47: FD100046 | B47: 31-10-2025 | C47: Delhi | D47: Desserts | E47: New | F47: UPI | G47: 466 | H47: 0 | I47: 40 | J47: 32 | K47: 4.4 | L47: Delivered
A48: FD100047 | B48: 45816 | C48: Delhi | D48: Fast Food | E48: Returning | F48: UPI | G48: 430 | H48: 90 | I48: 20 | J48: 23 | K48: 4.6 | L48: Delivered
A49: FD100048 | B49: 45778 | C49: Hyderabad | D49: Pizza | E49: New | F49: UPI | G49: 814 | H49: 188 | I49: 0 | J49: 40 | K49: 3.4 | L49: Delivered
A50: FD100049 | B50: 20-09-2025 | C50: Delhi | D50: Healthy | E50: Returning | F50: UPI | G50: 341 | H50: 72 | I50: 30 | J50: 27 | K50: 4.2 | L50: Delivered
A51: FD100050 | B51: 45718 | C51: Delhi | D51: Biryani | E51: New | F51: Credit Card | G51: 268 | H51: 53 | I51: 30 | J51: 35 | K51: 4.5 | L51: Delivered
A52: FD100051 | B52: 45743 | C52: Mumbai | D52: South Indian | E52: New | F52: Credit Card | G52: 399 | H52: 70 | I52: 45 | J52: 39 | K52: 4.2 | L52: Delivered
A53: FD100052 | B53: 45661 | C53: Bengaluru | D53: North Indian | E53: Returning | F53: Credit Card | G53: 423 | H53: 0 | I53: 20 | J53: 45 | K53: 2.9 | L53: Delivered
A54: FD100053 | B54: 45955 | C54: Delhi | D54: Pizza | E54: new | F54: Cash on Delivery | G54: 491 | H54: 0 | I54: 45 | J54: 42 | K54: 3.8 | L54: Delivered
A55: FD100054 | B55: 45914 | C55: Delhi | D55: Chinese | E55: returning | F55: UPI | G55: 322 | H55: 0 | I55: 30 | J55: 40 | K55: 4.7 | L55: Delivered
A56: FD100055 | B56: 45928 | C56: Delhi | D56: Pizza | E56: new | F56: UPI | G56: 734 | H56: 159 | I56: 0 | J56: 40 | K56: 4.4 | L56: Delivered
A57: FD100056 | B57: 45953 | C57: Chennai | D57: Fast Food | E57: Returning | F57: UPI | G57: 388 | H57: 0 | I57: 20 | J57: 25 | K57: 5 | L57: Delivered
A58: FD100057 | B58: 45842 | C58: Kolkata | D58: Pizza | E58: returning | F58: UPI | G58: 700 | H58: 0 | I58: 0 | J58: 37 | K58: 3.7 | L58: Delivered
A59: FD100058 | B59: 12-08-2025 | C59: Bengaluru | D59: North Indian | E59: Returning | F59: Debit Card | G59: 340 | H59: 79 | I59: 30 | J59: 31 | K59: 5 | L59: Delivered
A60: FD100059 | B60: 45718 | C60: Hyderabad | D60: Biryani | E60: New | F60: Cash on Delivery | G60: 630 | H60: 64 | I60: 0 | J60: 44 | K60: 4 | L60: Delivered
A61: FD100060 | B61: 20-02-2025 | C61: Pune | D61: Biryani | E61: Returning | F61: Wallet | G61: 471 | H61: 0 | I61: 45 | J61: 20 | K61: 5 | L61: Delivered
A62: FD100061 | B62: 45915 | C62: Ahmedabad | D62: Pizza | E62: Returning | F62: Debit Card | G62: 589 | H62: 0 | I62: 0 | J62: 26 | K62: 4.5 | L62: Delivered
A63: FD100062 | B63: 09-07-2025 | C63: Bengaluru | D63: Fast Food | E63: New | F63: UPI | G63: 515 | H63: 97 | I63: 0 | J63: 33 | K63: 3.3 | L63: Delivered
A64: FD100063 | B64: 45880 | C64: Pune | D64: Biryani | E64: New | F64: UPI | G64: 497 | H64: 0 | I64: 30 | J64: 25 | K64: 4.9 | L64: Delivered
A65: FD100064 | B65: 45948 | C65: Pune | D65: South Indian | E65: Returning | F65: UPI | G65: 421 | H65: 53 | I65: 40 | J65: 30 | K65: 4.2 | L65: Delivered
A66: FD100065 | B66: 45904 | C66: Chennai | D66: Fast Food | E66: New | F66: UPI | G66: 317 | H66: 0 | I66: 40 | J66: 27 | K66: 4.3 | L66: Delivered
A67: FD100066 | B67: 45876 | C67: Bengaluru | D67: Fast Food | E67: Returning | F67: Wallet | G67: 381 | H67: 51 | I67: 40 | J67: 50 | K67: 3.2 | L67: Delivered
A68: FD100067 | B68: 45878 | C68: Mumbai | D68: Fast Food | E68: Returning | F68: Credit Card | G68: 345 | H68: 53 | I68: 40 | J68: 40 | K68: 5 | L68: Delivered
A69: FD100068 | B69: 45784 | C69: Mumbai | D69: North Indian | E69: New | F69: UPI | G69: 724 | H69: 74 | I69: 0 | J69: 35 | K69: 4 | L69: Delivered
A70: FD100069 | B70: 45671 | C70: Bengaluru | D70: Chinese | E70: Returning | F70: UPI | G70: 430 | H70: 0 | I70: 45 | J70: 41 | K70: 4.9 | L70: Delivered
A71: FD100070 | B71: 45834 | C71: Bengaluru | D71: Fast Food | E71: returning | F71: UPI | G71: 452 | H71: 0 | I71: 40 | J71: 51 | K71: 3.7 | L71: Delivered
A72: FD100071 | B72: 45749 | C72: Bengaluru | D72: North Indian | E72: New | F72: Wallet | G72: 684 | H72: 0 | I72: 0 | J72: 48 | K72: 3.5 | L72: Delivered
A73: FD100072 | B73: 45823 | C73: Bengaluru | D73: Desserts | E73: Returning | F73: UPI | G73: 290 | H73: 0 | I73: 30 | J73: 34 | K73: 5 | L73: Delivered
A74: FD100073 | B74: 45976 | C74: Bengaluru | D74: South Indian | E74: New | F74: UPI | G74: 315 | H74: 56 | I74: 30 | J74: 37 | L74: Delivered
A75: FD100074 | B75: 45757 | C75: Chennai | D75: Chinese | E75: Returning | F75: UPI | G75: 579 | H75: 0 | I75: 0 | L75: Cancelled
A76: FD100075 | B76: 45683 | C76: Mumbai | D76: South Indian | E76: Returning | F76: Cash on Delivery | G76: 314 | H76: 0 | I76: 45 | J76: 40 | K76: 3.5 | L76: Delivered
A77: FD100076 | B77: 45775 | C77: delhi | D77: Healthy | E77: New | F77: Credit Card | G77: 535 | H77: 81 | I77: 0 | J77: 29 | K77: 4.2 | L77: Delivered
A78: FD100077 | B78: 45780 | C78: Chennai | D78: Biryani | E78: Returning | F78: Debit Card | G78: 501 | H78: 0 | I78: 0 | J78: 36 | K78: 4.5 | L78: Delivered
A79: FD100078 | B79: 45913 | C79: Pune | D79: Pizza | E79: New | F79: UPI | G79: 599 | H79: 64 | I79: 0 | J79: 24 | K79: 3.9 | L79: Delivered
A80: FD100079 | B80: 45877 | C80: Ahmedabad | D80: Pizza | E80: Returning | F80: UPI | G80: 631 | H80: 0 | I80: 0 | J80: 37 | K80: 4 | L80: Delivered
A81: FD100080 | B81: 45954 | C81: Pune | D81: Biryani | E81: New | F81: Cash on Delivery | G81: 587 | H81: 143 | I81: 0 | J81: 34 | K81: 4.1 | L81: Delivered
A82: FD100081 | B82: 45914 | C82: Pune | D82: Biryani | E82: Returning | F82: UPI | G82: 357 | H82: 0 | I82: 20 | J82: 22 | K82: 4.6 | L82: Delivered
A83: FD100082 | B83: 45823 | C83: Delhi | D83: North Indian | E83: Returning | F83: UPI | G83: 408 | H83: 99 | I83: 40 | J83: 32 | K83: 5 | L83: Delivered
A84: FD100083 | B84: 45964 | C84: Bengaluru | D84: Pizza | E84: Returning | F84: Debit Card | G84: 538 | H84: 0 | I84: 0 | J84: 38 | L84: Delivered
A85: FD100084 | B85: 45730 | C85: Delhi | D85: Chinese | E85: Returning | F85: UPI | G85: 307 | H85: 0 | I85: 20 | J85: 37 | L85: Delivered
A86: FD100085 | B86: 45668 | C86: Bengaluru | D86: Chinese | E86: Returning | F86: UPI | G86: 548 | H86: 0 | I86: 0 | J86: 41 | K86: 5 | L86: Delivered
A87: FD100086 | B87: 45697 | C87: Kolkata | D87: Biryani | E87: Returning | F87: Cash on Delivery | G87: 400 | H87: 42 | I87: 30 | J87: 27 | K87: 4.3 | L87: Delivered
A88: FD100087 | B88: 45934 | C88: Delhi | D88: Biryani | E88: Returning | F88: Credit Card | G88: 545 | H88: 74 | I88: 0 | J88: 26 | K88: 4.4 | L88: Delivered
A89: FD100088 | B89: 45843 | C89: Bengaluru | D89: Fast Food | E89: Returning | F89: UPI | G89: 408 | H89: 0 | I89: 20 | J89: 46 | K89: 3.8 | L89: Delivered
A90: FD100089 | B90: 45727 | C90: Delhi | D90: Pizza | E90: Returning | F90: UPI | G90: 790 | H90: 0 | I90: 0 | J90: 38 | K90: 4.1 | L90: Delivered
A91: FD100090 | B91: 45857 | C91: Mumbai | D91: Healthy | E91: Returning | F91: Cash on Delivery | G91: 394 | H91: 0 | I91: 20 | J91: 39 | K91: 4.2 | L91: Delivered
A92: FD100091 | B92: 45723 | C92: Mumbai | D92: South Indian | E92: New | F92: UPI | G92: 255 | H92: 49 | I92: 30 | L92: Cancelled
A93: FD100092 | B93: 45925 | C93: Mumbai | D93: Healthy | E93: returning | F93: UPI | G93: 675 | H93: 86 | I93: 0 | J93: 34 | K93: 4.5 | L93: Delivered
A94: FD100093 | B94: 45837 | C94: Kolkata | D94: South Indian | E94: Returning | F94: Debit Card | G94: 322 | H94: 48 | I94: 40 | J94: 36 | K94: 4.8 | L94: Delivered
A95: FD100094 | B95: 45814 | C95: Bengaluru | D95: Desserts | E95: New | F95: Debit Card | G95: 202 | H95: 0 | I95: 45 | J95: 60 | K95: 4.2 | L95: Delivered
A96: FD100095 | B96: 45783 | C96: Chennai | D96: Fast Food | E96: New | F96: Wallet | G96: 416 | H96: 85 | I96: 20 | J96: 39 | K96: 4.3 | L96: Delivered
A97: FD100096 | B97: 45903 | C97: Hyderabad | D97: North Indian | E97: Returning | F97: UPI | G97: 516 | H97: 0 | I97: 0 | J97: 31 | K97: 4.6 | L97: Delivered
A98: FD100097 | B98: 45806 | C98: Mumbai | D98: North Indian | E98: Returning | F98: UPI | G98: 513 | H98: 0 | I98: 0 | J98: 34 | K98: 4.9 | L98: Delivered
A99: FD100098 | B99: 08-02-2025 | C99: Mumbai | D99: Fast Food | E99: New | F99: Credit Card | G99: 224 | H99: 24 | I99: 40 | J99: 18 | K99: 4.1 | L99: Delivered
A100: FD100099 | B100: 45709 | C100: Chennai | D100: Biryani | E100: New | F100: Debit Card | G100: 496 | H100: 81 | I100: 30 | J100: 38 | K100: 5 | L100: Delivered
A101: FD100100 | B101: 46011 | C101: Delhi | D101: North Indian | E101: Returning | F101: UPI | G101: 515 | H101: 126 | I101: 0 | J101: 42 | K101: 3.8 | L101: Delivered
A102: FD100101 | B102: 45994 | C102: Kolkata | D102: Desserts | E102: Returning | F102: Credit Card | G102: 488 | H102: 53 | I102: 30 | J102: 31 | K102: 4.2 | L102: Delivered
...

Sheet Cleaned Data
A1: Order_ID | B1: Order_Date | C1: Month | D1: Weekday | E1: City | F1: Cuisine | G1: Customer_Type | H1: Payment_Method | I1: Order_Value | J1: Discount | K1: Delivery_Fee | L1: Net_Revenue | M1: Delivery_Time_Min | N1: Rating | O1: Order_Status
A2: FD100741 | B2: 45658 | C2: =TEXT(B2,"mmm") -> Jan | D2: =TEXT(B2,"ddd") -> Wed | E2: Delhi | F2: Biryani | G2: New | H2: Debit Card | I2: 310 | J2: 74 | K2: 40 | L2: =IF(O2="Delivered",I2-J2+K2,0) -> 276 | M2: 30 | N2: 5 | O2: Delivered
A3: FD100744 | B3: 45658 | C3: =TEXT(B3,"mmm") -> Jan | D3: =TEXT(B3,"ddd") -> Wed | E3: Delhi | F3: Fast Food | G3: New | H3: UPI | I3: 353 | J3: 54 | K3: 40 | L3: =IF(O3="Delivered",I3-J3+K3,0) -> 339 | M3: 46 | N3: 3.3 | O3: Delivered
A4: FD101158 | B4: 45658 | C4: =TEXT(B4,"mmm") -> Jan | D4: =TEXT(B4,"ddd") -> Wed | E4: Bengaluru | F4: North Indian | G4: Returning | H4: Wallet | I4: 408 | J4: 53 | K4: 20 | L4: =IF(O4="Delivered",I4-J4+K4,0) -> 375 | M4: 50 | N4: 3.5 | O4: Delivered
A5: FD101221 | B5: 45658 | C5: =TEXT(B5,"mmm") -> Jan | D5: =TEXT(B5,"ddd") -> Wed | E5: Bengaluru | F5: North Indian | G5: Returning | H5: UPI | I5: 531 | J5: 0 | K5: 0 | L5: =IF(O5="Delivered",I5-J5+K5,0) -> 531 | M5: 52 | N5: 2.8 | O5: Delivered
A6: FD100423 | B6: 45660 | C6: =TEXT(B6,"mmm") -> Jan | D6: =TEXT(B6,"ddd") -> Fri | E6: Bengaluru | F6: Pizza | G6: New | H6: Debit Card | I6: 805 | J6: 0 | K6: 0 | L6: =IF(O6="Delivered",I6-J6+K6,0) -> 0 | O6: Cancelled
A7: FD100647 | B7: 45660 | C7: =TEXT(B7,"mmm") -> Jan | D7: =TEXT(B7,"ddd") -> Fri | E7: Mumbai | F7: Biryani | G7: Returning | H7: UPI | I7: 369 | J7: 56 | K7: 45 | L7: =IF(O7="Delivered",I7-J7+K7,0) -> 358 | M7: 32 | N7: 4.5 | O7: Delivered
A8: FD100775 | B8: 45660 | C8: =TEXT(B8,"mmm") -> Jan | D8: =TEXT(B8,"ddd") -> Fri | E8: Pune | F8: South Indian | G8: Returning | H8: Credit Card | I8: 347 | J8: 0 | K8: 30 | L8: =IF(O8="Delivered",I8-J8+K8,0) -> 377 | M8: 35 | N8: 4.3 | O8: Delivered
A9: FD100811 | B9: 45660 | C9: =TEXT(B9,"mmm") -> Jan | D9: =TEXT(B9,"ddd") -> Fri | E9: Ahmedabad | F9: Pizza | G9: Returning | H9: UPI | I9: 374 | J9: 0 | K9: 30 | L9: =IF(O9="Delivered",I9-J9+K9,0) -> 404 | M9: 32 | N9: 4.7 | O9: Delivered
A10: FD101314 | B10: 45660 | C10: =TEXT(B10,"mmm") -> Jan | D10: =TEXT(B10,"ddd") -> Fri | E10: Mumbai | F10: South Indian | G10: Returning | H10: Debit Card | I10: 301 | J10: 73 | K10: 20 | L10: =IF(O10="Delivered",I10-J10+K10,0) -> 248 | M10: 23 | N10: 5 | O10: Delivered
A11: FD101323 | B11: 45660 | C11: =TEXT(B11,"mmm") -> Jan | D11: =TEXT(B11,"ddd") -> Fri | E11: Mumbai | F11: Pizza | G11: Returning | H11: UPI | I11: 693 | J11: 0 | K11: 0 | L11: =IF(O11="Delivered",I11-J11+K11,0) -> 693 | M11: 40 | N11: 5 | O11: Delivered
A12: FD100052 | B12: 45661 | C12: =TEXT(B12,"mmm") -> Jan | D12: =TEXT(B12,"ddd") -> Sat | E12: Bengaluru | F12: North Indian | G12: Returning | H12: Credit Card | I12: 423 | J12: 0 | K12: 20 | L12: =IF(O12="Delivered",I12-J12+K12,0) -> 443 | M12: 45 | N12: 2.9 | O12: Delivered
A13: FD100595 | B13: 45661 | C13: =TEXT(B13,"mmm") -> Jan | D13: =TEXT(B13,"ddd") -> Sat | E13: Pune | F13: North Indian | G13: Returning | H13: Wallet | I13: 431 | J13: 0 | K13: 20 | L13: =IF(O13="Delivered",I13-J13+K13,0) -> 451 | M13: 26 | N13: 5 | O13: Delivered
A14: FD101101 | B14: 45661 | C14: =TEXT(B14,"mmm") -> Jan | D14: =TEXT(B14,"ddd") -> Sat | E14: Bengaluru | F14: Biryani | G14: Returning | H14: UPI | I14: 364 | J14: 0 | K14: 45 | L14: =IF(O14="Delivered",I14-J14+K14,0) -> 409 | M14: 54 | N14: 3.7 | O14: Delivered
A15: FD100535 | B15: 45662 | C15: =TEXT(B15,"mmm") -> Jan | D15: =TEXT(B15,"ddd") -> Sun | E15: Mumbai | F15: Chinese | G15: Returning | H15: Credit Card | I15: 478 | J15: 94 | K15: 40 | L15: =IF(O15="Delivered",I15-J15+K15,0) -> 424 | M15: 33 | N15: 4.5 | O15: Delivered
A16: FD100766 | B16: 45662 | C16: =TEXT(B16,"mmm") -> Jan | D16: =TEXT(B16,"ddd") -> Sun | E16: Mumbai | F16: South Indian | G16: New | H16: Debit Card | I16: 261 | J16: 28 | K16: 30 | L16: =IF(O16="Delivered",I16-J16+K16,0) -> 263 | M16: 37 | N16: 4.6 | O16: Delivered
A17: FD100395 | B17: 45663 | C17: =TEXT(B17,"mmm") -> Jan | D17: =TEXT(B17,"ddd") -> Mon | E17: Delhi | F17: Chinese | G17: Returning | H17: Debit Card | I17: 270 | J17: 0 | K17: 45 | L17: =IF(O17="Delivered",I17-J17+K17,0) -> 315 | M17: 33 | N17: 3.8 | O17: Delivered
A18: FD100841 | B18: 45663 | C18: =TEXT(B18,"mmm") -> Jan | D18: =TEXT(B18,"ddd") -> Mon | E18: Mumbai | F18: Chinese | G18: New | H18: Cash on Delivery | I18: 413 | J18: 72 | K18: 45 | L18: =IF(O18="Delivered",I18-J18+K18,0) -> 386 | M18: 41 | N18: 3.5 | O18: Delivered
... A24: FD100797 | B24: 45666 | C24: =TEXT(B24,"mmm") -> Jan | D24: =TEXT(B24,"ddd") -> Thu | E24: Hyderabad | F24: Pizza | G24: Returning | H24: Cash on Delivery | I24: 713 | J24: 0 | K24: 0 | L24: =IF(O24="Delivered",I24-J24+K24,0) -> 713 | M24: 35 | N24: 3.9 | O24: Delivered
A25: FD100826 | B25: 45666 | C25: =TEXT(B25,"mmm") -> Jan | D25: =TEXT(B25,"ddd") -> Thu | E25: Ahmedabad | F25: Pizza | G25: New | H25: Credit Card | I25: 670 | J25: 0 | K25: 0 | L25: =IF(O25="Delivered",I25-J25+K25,0) -> 670 | M25: 30 | O25: Delivered
A26: FD101045 | B26: 45666 | C26: =TEXT(B26,"mmm") -> Jan | D26: =TEXT(B26,"ddd") -> Thu | E26: Bengaluru | F26: Fast Food | G26: Returning | H26: Wallet | I26: 291 | J26: 58 | K26: 40 | L26: =IF(O26="Delivered",I26-J26+K26,0) -> 273 | M26: 28 | N26: 4.8 | O26: Delivered
A27: FD100150 | B27: 45667 | C27: =TEXT(B27,"mmm") -> Jan | D27: =TEXT(B27,"ddd") -> Fri | E27: Chennai | F27: North Indian | G27: Returning | H27: Cash on Delivery | I27: 564 | J27: 0 | K27: 0 | L27: =IF(O27="Delivered",I27-J27+K27,0) -> 564 | M27: 24 | N27: 4.2 | O27: Delivered
A28: FD100270 | B28: 45667 | C28: =TEXT(B28,"mmm") -> Jan | D28: =TEXT(B28,"ddd") -> Fri | E28: Chennai | F28: North Indian | G28: Returning | H28: Unknown | I28: 675 | J28: 0 | K28: 0 | L28: =IF(O28="Delivered",I28-J28+K28,0) -> 675 | M28: 31 | O28: Delivered
A29: FD100085 | B29: 45668 | C29: =TEXT(B29,"mmm") -> Jan | D29: =TEXT(B29,"ddd") -> Sat | E29: Bengaluru | F29: Chinese | G29: Returning | H29: UPI | I29: 548 | J29: 0 | K29: 0 | L29: =IF(O29="Delivered",I29-J29+K29,0) -> 548 | M29: 41 | N29: 5 | O29: Delivered
A30: FD100136 | B30: 45668 | C30: =TEXT(B30,"mmm") -> Jan | D30: =TEXT(B30,"ddd") -> Sat | E30: Bengaluru | F30: Chinese | G30: New | H30: UPI | I30: 465 | J30: 0 | K30: 45 | L30: =IF(O30="Delivered",I30-J30+K30,0) -> 510 | M30: 29 | O30: Delivered
A31: FD100227 | B31: 45668 | C31: =TEXT(B31,"mmm") -> Jan | D31: =TEXT(B31,"ddd") -> Sat | E31: Delhi | F31: Chinese | G31: Returning | H31: Credit Card | I31: 460 | J31: 0 | K31: 20 | L31: =IF(O31="Delivered",I31-J31+K31,0) -> 480 | M31: 31 | O31: Delivered
A32: FD100590 | B32: 45668 | C32: =TEXT(B32,"mmm") -> Jan | D32: =TEXT(B32,"ddd") -> Sat | E32: Bengaluru | F32: Biryani | G32: New | H32: Credit Card | I32: 315 | J32: 0 | K32: 45 | L32: =IF(O32="Delivered",I32-J32+K32,0) -> 360 | M32: 41 | O32: Delivered
A33: FD100872 | B33: 45668 | C33: =TEXT(B33,"mmm") -> Jan | D33: =TEXT(B33,"ddd") -> Sat | E33: Delhi | F33: Biryani | G33: Returning | H33: Credit Card | I33: 491 | J33: 0 | K33: 30 | L33: =IF(O33="Delivered",I33-J33+K33,0) -> 521 | M33: 32 | N33: 5 | O33: Delivered
A34: FD101069 | B34: 45668 | C34: =TEXT(B34,"mmm") -> Jan | D34: =TEXT(B34,"ddd") -> Sat | E34: Hyderabad | F34: Healthy | G34: New | H34: Credit Card | I34: 477 | J34: 81 | K34: 30 | L34: =IF(O34="Delivered",I34-J34+K34,0) -> 426 | M34: 35 | N34: 4.3 | O34: Delivered
A35: FD101356 | B35: 45668 | C35: =TEXT(B35,"mmm") -> Jan | D35: =TEXT(B35,"ddd") -> Sat | E35: Kolkata | F35: Chinese | G35: Returning | H35: UPI | I35: 505 | J35: 108 | K35: 0 | L35: =IF(O35="Delivered",I35-J35+K35,0) -> 397 | M35: 30 | N35: 5 | O35: Delivered
A36: FD101205 | B36: 45669 | C36: =TEXT(B36,"mmm") -> Jan | D36: =TEXT(B36,"ddd") -> Sun | E36: Hyderabad | F36: Chinese | G36: Returning | H36: Debit Card | I36: 520 | J36: 0 | K36: 0 | L36: =IF(O36="Delivered",I36-J36+K36,0) -> 520 | M36: 19 | N36: 4.5 | O36: Delivered
A37: FD101318 | B37: 45669 | C37: =TEXT(B37,"mmm") -> Jan | D37: =TEXT(B37,"ddd") -> Sun | E37: Bengaluru | F37: Chinese | G37: New | H37: Wallet | I37: 520 | J37: 79 | K37: 0 | L37: =IF(O37="Delivered",I37-J37+K37,0) -> 441 | M37: 35 | N37: 4.3 | O37: Delivered
A38: FD100415 | B38: 45670 | C38: =TEXT(B38,"mmm") -> Jan | D38: =TEXT(B38,"ddd") -> Mon | E38: Mumbai | F38: Biryani | G38: New | H38: Credit Card | I38: 551 | J38: 115 | K38: 0 | L38: =IF(O38="Delivered",I38-J38+K38,0) -> 436 | M38: 36 | N38: 5 | O38: Delivered
A39: FD100650 | B39: 45670 | C39: =TEXT(B39,"mmm") -> Jan | D39: =TEXT(B39,"ddd") -> Mon | E39: Mumbai | F39: South Indian | G39: New | H39: UPI | I39: 228 | J39: 0 | K39: 20 | L39: =IF(O39="Delivered",I39-J39+K39,0) -> 248 | M39: 38 | N39: 4.1 | O39: Delivered
A40: FD100069 | B40: 45671 | C40: =TEXT(B40,"mmm") -> Jan | D40: =TEXT(B40,"ddd") -> Tue | E40: Bengaluru | F40: Chinese | G40: Returning | H40: UPI | I40: 430 | J40: 0 | K40: 45 | L40: =IF(O40="Delivered",I40-J40+K40,0) -> 475 | M40: 41 | N40: 4.9 | O40: Delivered
A41: FD100768 | B41: 45671 | C41: =TEXT(B41,"mmm") -> Jan | D41: =TEXT(B41,"ddd") -> Tue | E41: Bengaluru | F41: Biryani | G41: Returning | H41: Credit Card | I41: 536 | J41: 0 | K41: 0 | L41: =IF(O41="Delivered",I41-J41+K41,0) -> 536 | M41: 32 | N41: 4.4 | O41: Delivered
A42: FD100795 | B42: 45671 | C42: =TEXT(B42,"mmm") -> Jan | D42: =TEXT(B42,"ddd") -> Tue | E42: Delhi | F42: Pizza | G42: Returning | H42: Debit Card | I42: 491 | J42: 58 | K42: 20 | L42: =IF(O42="Delivered",I42-J42+K42,0) -> 453 | M42: 39 | N42: 4.2 | O42: Delivered
A43: FD100972 | B43: 45671 | C43: =TEXT(B43,"mmm") -> Jan | D43: =TEXT(B43,"ddd") -> Tue | E43: Pune | F43: North Indian | G43: New | H43: UPI | I43: 579 | J43: 103 | K43: 0 | L43: =IF(O43="Delivered",I43-J43+K43,0) -> 476 | M43: 12 | N43: 4.5 | O43: Delivered
A44: FD101161 | B44: 45673 | C44: =TEXT(B44,"mmm") -> Jan | D44: =TEXT(B44,"ddd") -> Thu | E44: Pune | F44: Fast Food | G44: Returning | H44: Debit Card | I44: 396 | J44: 0 | K44: 40 | L44: =IF(O44="Delivered",I44-J44+K44,0) -> 436 | M44: 36 | N44: 4.3 | O44: Delivered
... A58: FD100451 | B58: 45676 | C58: =TEXT(B58,"mmm") -> Jan | D58: =TEXT(B58,"ddd") -> Sun | E58: Kolkata | F58: Chinese | G58: New | H58: UPI | I58: 573 | J58: 0 | K58: 0 | L58: =IF(O58="Delivered",I58-J58+K58,0) -> 573 | M58: 30 | N58: 4.5 | O58: Delivered
A59: FD100620 | B59: 45676 | C59: =TEXT(B59,"mmm") -> Jan | D59: =TEXT(B59,"ddd") -> Sun | E59: Delhi | F59: Desserts | G59: Returning | H59: UPI | I59: 440 | J59: 0 | K59: 40 | L59: =IF(O59="Delivered",I59-J59+K59,0) -> 480 | M59: 24 | O59: Delivered
A60: FD100726 | B60: 45676 | C60: =TEXT(B60,"mmm") -> Jan | D60: =TEXT(B60,"ddd") -> Sun | E60: Delhi | F60: South Indian | G60: Returning | H60: UPI | I60: 306 | J60: 42 | K60: 20 | L60: =IF(O60="Delivered",I60-J60+K60,0) -> 0 | O60: Cancelled
A61: FD100028 | B61: 45677 | C61: =TEXT(B61,"mmm") -> Jan | D61: =TEXT(B61,"ddd") -> Mon | E61: Bengaluru | F61: South Indian | G61: Returning | H61: UPI | I61: 367 | J61: 0 | K61: 40 | L61: =IF(O61="Delivered",I61-J61+K61,0) -> 0 | O61: Cancelled
A62: FD100176 | B62: 45677 | C62: =TEXT(B62,"mmm") -> Jan | D62: =TEXT(B62,"ddd") -> Mon | E62: Kolkata | F62: North Indian | G62: New | H62: Wallet | I62: 383 | J62: 0 | K62: 30 | L62: =IF(O62="Delivered",I62-J62+K62,0) -> 413 | M62: 28 | N62: 4.6 | O62: Delivered
A63: FD100281 | B63: 45677 | C63: =TEXT(B63,"mmm") -> Jan | D63: =TEXT(B63,"ddd") -> Mon | E63: Mumbai | F63: Chinese | G63: New | H63: Cash on Delivery | I63: 508 | J63: 95 | K63: 0 | L63: =IF(O63="Delivered",I63-J63+K63,0) -> 413 | M63: 48 | N63: 4 | O63: Delivered
A64: FD100555 | B64: 45677 | C64: =TEXT(B64,"mmm") -> Jan | D64: =TEXT(B64,"ddd") -> Mon | E64: Delhi | F64: Biryani | G64: Returning | H64: UPI | I64: 568 | J64: 0 | K64: 0 | L64: =IF(O64="Delivered",I64-J64+K64,0) -> 0 | O64: Cancelled
A65: FD100903 | B65: 45677 | C65: =TEXT(B65,"mmm") -> Jan | D65: =TEXT(B65,"ddd") -> Mon | E65: Hyderabad | F65: Chinese | G65: Returning | H65: Cash on Delivery | I65: 413 | J65: 0 | K65: 20 | L65: =IF(O65="Delivered",I65-J65+K65,0) -> 433 | M65: 37 | N65: 4.3 | O65: Delivered
A66: FD101261 | B66: 45677 | C66: =TEXT(B66,"mmm") -> Jan | D66: =TEXT(B66,"ddd") -> Mon | E66: Hyderabad | F66: Desserts | G66: New | H66: Wallet | I66: 368 | J66: 37 | K66: 20 | L66: =IF(O66="Delivered",I66-J66+K66,0) -> 351 | M66: 27 | N66: 5 | O66: Delivered
A67: FD101390 | B67: 45677 | C67: =TEXT(B67,"mmm") -> Jan | D67: =TEXT(B67,"ddd") -> Mon | E67: Mumbai | F67: Pizza | G67: New | H67: UPI | I67: 800 | J67: 139 | K67: 0 | L67: =IF(O67="Delivered",I67-J67+K67,0) -> 661 | M67: 44 | N67: 3.4 | O67: Delivered
A68: FD100763 | B68: 45678 | C68: =TEXT(B68,"mmm") -> Jan | D68: =TEXT(B68,"ddd") -> Tue | E68: Bengaluru | F68: North Indian | G68: New | H68: Wallet | I68: 395 | J68: 92 | K68: 30 | L68: =IF(O68="Delivered",I68-J68+K68,0) -> 333 | M68: 34 | N68: 4.2 | O68: Delivered
A69: FD100287 | B69: 45679 | C69: =TEXT(B69,"mmm") -> Jan | D69: =TEXT(B69,"ddd") -> Wed | E69: Delhi | F69: Pizza | G69: New | H69: Credit Card | I69: 714 | J69: 0 | K69: 0 | L69: =IF(O69="Delivered",I69-J69+K69,0) -> 714 | M69: 32 | N69: 4.3 | O69: Delivered
A70: FD100635 | B70: 45679 | C70: =TEXT(B70,"mmm") -> Jan | D70: =TEXT(B70,"ddd") -> Wed | E70: Bengaluru | F70: Pizza | G70: Returning | H70: Cash on Delivery | I70: 519 | J70: 0 | K70: 0 | L70: =IF(O70="Delivered",I70-J70+K70,0) -> 519 | M70: 50 | N70: 3.8 | O70: Delivered
A71: FD100643 | B71: 45679 | C71: =TEXT(B71,"mmm") -> Jan | D71: =TEXT(B71,"ddd") -> Wed | E71: Chennai | F71: South Indian | G71: New | H71: UPI | I71: 333 | J71: 63 | K71: 45 | L71: =IF(O71="Delivered",I71-J71+K71,0) -> 315 | M71: 27 | O71: Delivered
A72: FD100759 | B72: 45679 | C72: =TEXT(B72,"mmm") -> Jan | D72: =TEXT(B72,"ddd") -> Wed | E72: Mumbai | F72: Healthy | G72: Returning | H72: UPI | I72: 447 | J72: 96 | K72: 45 | L72: =IF(O72="Delivered",I72-J72+K72,0) -> 396 | M72: 48 | N72: 3.3 | O72: Delivered
A73: FD101206 | B73: 45679 | C73: =TEXT(B73,"mmm") -> Jan | D73: =TEXT(B73,"ddd") -> Wed | E73: Bengaluru | F73: Chinese | G73: Returning | H73: UPI | I73: 464 | J73: 0 | K73: 40 | L73: =IF(O73="Delivered",I73-J73+K73,0) -> 504 | M73: 41 | N73: 3.8 | O73: Delivered
A74: FD101442 | B74: 45679 | C74: =TEXT(B74,"mmm") -> Jan | D74: =TEXT(B74,"ddd") -> Wed | E74: Delhi | F74: Biryani | G74: Returning | H74: Cash on Delivery | I74: 421 | J74: 78 | K74: 40 | L74: =IF(O74="Delivered",I74-J74+K74,0) -> 383 | M74: 34 | N74: 5 | O74: Delivered
A75: FD100732 | B75: 45680 | C75: =TEXT(B75,"mmm") -> Jan | D75: =TEXT(B75,"ddd") -> Thu | E75: Hyderabad | F75: Healthy | G75: Returning | H75: Credit Card | I75: 614 | J75: 83 | K75: 0 | L75: =IF(O75="Delivered",I75-J75+K75,0) -> 531 | M75: 40 | N75: 4.1 | O75: Delivered
A76: FD100821 | B76: 45680 | C76: =TEXT(B76,"mmm") -> Jan | D76: =TEXT(B76,"ddd") -> Thu | E76: Mumbai | F76: Chinese | G76: New | H76: Debit Card | I76: 312 | J76: 64 | K76: 20 | L76: =IF(O76="Delivered",I76-J76+K76,0) -> 268 | M76: 37 | N76: 4.4 | O76: Delivered
A77: FD100988 | B77: 45680 | C77: =TEXT(B77,"mmm") -> Jan | D77: =TEXT(B77,"ddd") -> Thu | E77: Chennai | F77: Fast Food | G77: New | H77: UPI | I77: 378 | J77: 52 | K77: 20 | L77: =IF(O77="Delivered",I77-J77+K77,0) -> 346 | M77: 29 | N77: 4.1 | O77: Delivered
A78: FD101139 | B78: 45680 | C78: =TEXT(B78,"mmm") -> Jan | D78: =TEXT(B78,"ddd") -> Thu | E78: Chennai | F78: Chinese | G78: New | H78: Cash on Delivery | I78: 364 | J78: 77 | K78: 40 | L78: =IF(O78="Delivered",I78-J78+K78,0) -> 327 | M78: 20 | N78: 5 | O78: Delivered
A79: FD101486 | B79: 45680 | C79: =TEXT(B79,"mmm") -> Jan | D79: =TEXT(B79,"ddd") -> Thu | E79: Delhi | F79: Biryani | G79: Returning | H79: Cash on Delivery | I79: 439 | J79: 0 | K79: 45 | L79: =IF(O79="Delivered",I79-J79+K79,0) -> 484 | M79: 36 | N79: 4.7 | O79: Delivered
A80: FD100273 | B80: 45681 | C80: =TEXT(B80,"mmm") -> Jan | D80: =TEXT(B80,"ddd") -> Fri | E80: Hyderabad | F80: Pizza | G80: New | H80: Debit Card | I80: 563 | J80: 129 | K80: 0 | L80: =IF(O80="Delivered",I80-J80+K80,0) -> 434 | M80: 41 | N80: 3.8 | O80: Delivered
A81: FD100292 | B81: 45681 | C81: =TEXT(B81,"mmm") -> Jan | D81: =TEXT(B81,"ddd") -> Fri | E81: Delhi | F81: Chinese | G81: New | H81: Wallet | I81: 314 | J81: 34 | K81: 40 | L81: =IF(O81="Delivered",I81-J81+K81,0) -> 0 | O81: Cancelled
A82: FD100424 | B82: 45681 | C82: =TEXT(B82,"mmm") -> Jan | D82: =TEXT(B82,"ddd") -> Fri | E82: Delhi | F82: Fast Food | G82: Returning | H82: Cash on Delivery | I82: 304 | J82: 66 | K82: 40 | L82: =IF(O82="Delivered",I82-J82+K82,0) -> 278 | M82: 43 | N82: 3.8 | O82: Delivered
A83: FD101157 | B83: 45681 | C83: =TEXT(B83,"mmm") -> Jan | D83: =TEXT(B83,"ddd") -> Fri | E83: Delhi | F83: Healthy | G83: Returning | H83: Cash on Delivery | I83: 354 | J83: 0 | K83: 45 | L83: =IF(O83="Delivered",I83-J83+K83,0) -> 399 | M83: 38 | N83: 4.1 | O83: Delivered
A84: FD101309 | B84: 45681 | C84: =TEXT(B84,"mmm") -> Jan | D84: =TEXT(B84,"ddd") -> Fri | E84: Mumbai | F84: Healthy | G84: New | H84: UPI | I84: 407 | J84: 0 | K84: 30 | L84: =IF(O84="Delivered",I84-J84+K84,0) -> 437 | M84: 34 | N84: 3.9 | O84: Delivered
A85: FD100271 | B85: 45682 | C85: =TEXT(B85,"mmm") -> Jan | D85: =TEXT(B85,"ddd") -> Sat | E85: Bengaluru | F85: Desserts | G85: Returning | H85: Credit Card | I85: 235 | J85: 38 | K85: 20 | L85: =IF(O85="Delivered",I85-J85+K85,0) -> 217 | M85: 57 | N85: 3.5 | O85: Delivered
A86: FD100449 | B86: 45682 | C86: =TEXT(B86,"mmm") -> Jan | D86: =TEXT(B86,"ddd") -> Sat | E86: Mumbai | F86: Biryani | G86: Returning | H86: Cash on Delivery | I86: 435 | J86: 0 | K86: 45 | L86: =IF(O86="Delivered",I86-J86+K86,0) -> 480 | M86: 38 | N86: 4.6 | O86: Delivered
A87: FD100513 | B87: 45682 | C87: =TEXT(B87,"mmm") -> Jan | D87: =TEXT(B87,"ddd") -> Sat | E87: Mumbai | F87: Desserts | G87: New | H87: UPI | I87: 470 | J87: 52 | K87: 30 | L87: =IF(O87="Delivered",I87-J87+K87,0) -> 448 | M87: 26 | O87: Delivered
A88: FD101244 | B88: 45682 | C88: =TEXT(B88,"mmm") -> Jan | D88: =TEXT(B88,"ddd") -> Sat | E88: Chennai | F88: Fast Food | G88: Returning | H88: Cash on Delivery | I88: 349 | J88: 78 | K88: 40 | L88: =IF(O88="Delivered",I88-J88+K88,0) -> 311 | M88: 31 | N88: 4.4 | O88: Delivered
A89: FD100075 | B89: 45683 | C89: =TEXT(B89,"mmm") -> Jan | D89: =TEXT(B89,"ddd") -> Sun | E89: Mumbai | F89: South Indian | G89: Returning | H89: Cash on Delivery | I89: 314 | J89: 0 | K89: 45 | L89: =IF(O89="Delivered",I89-J89+K89,0) -> 359 | M89: 40 | N89: 3.5 | O89: Delivered
A90: FD100429 | B90: 45683 | C90: =TEXT(B90,"mmm") -> Jan | D90: =TEXT(B90,"ddd") -> Sun | E90: Mumbai | F90: Healthy | G90: Returning | H90: Credit Card | I90: 491 | J90: 86 | K90: 45 | L90: =IF(O90="Delivered",I90-J90+K90,0) -> 450 | M90: 49 | N90: 4.4 | O90: Delivered
A91: FD100568 | B91: 45683 | C91: =TEXT(B91,"mmm") -> Jan | D91: =TEXT(B91,"ddd") -> Sun | E91: Ahmedabad | F91: Fast Food | G91: Returning | H91: Credit Card | I91: 529 | J91: 0 | K91: 0 | L91: =IF(O91="Delivered",I91-J91+K91,0) -> 529 | M91: 31 | N91: 4.6 | O91: Delivered
A92: FD100735 | B92: 45684 | C92: =TEXT(B92,"mmm") -> Jan | D92: =TEXT(B92,"ddd") -> Mon | E92: Hyderabad | F92: North Indian | G92: Returning | H92: UPI | I92: 310 | J92: 39 | K92: 20 | L92: =IF(O92="Delivered",I92-J92+K92,0) -> 291 | M92: 26 | N92: 4.7 | O92: Delivered
A93: FD101230 | B93: 45684 | C93: =TEXT(B93,"mmm") -> Jan | D93: =TEXT(B93,"ddd") -> Mon | E93: Pune | F93: Biryani | G93: New | H93: Wallet | I93: 446 | J93: 76 | K93: 30 | L93: =IF(O93="Delivered",I93-J93+K93,0) -> 400 | M93: 30 | N93: 3.5 | O93: Delivered
A94: FD101394 | B94: 45684 | C94: =TEXT(B94,"mmm") -> Jan | D94: =TEXT(B94,"ddd") -> Mon | E94: Bengaluru | F94: Pizza | G94: Returning | H94: Cash on Delivery | I94: 647 | J94: 92 | K94: 0 | L94: =IF(O94="Delivered",I94-J94+K94,0) -> 555 | M94: 33 | N94: 4.2 | O94: Delivered
A95: FD101491 | B95: 45684 | C95: =TEXT(B95,"mmm") -> Jan | D95: =TEXT(B95,"ddd") -> Mon | E95: Chennai | F95: Fast Food | G95: New | H95: Wallet | I95: 423 | J95: 0 | K95: 40 | L95: =IF(O95="Delivered",I95-J95+K95,0) -> 463 | M95: 25 | N95: 4.2 | O95: Delivered
A96: FD101001 | B96: 45685 | C96: =TEXT(B96,"mmm") -> Jan | D96: =TEXT(B96,"ddd") -> Tue | E96: Mumbai | F96: Chinese | G96: New | H96: Cash on Delivery | I96: 488 | J96: 55 | K96: 20 | L96: =IF(O96="Delivered",I96-J96+K96,0) -> 453 | M96: 30 | N96: 4.3 | O96: Delivered
A97: FD101402 | B97: 45685 | C97: =TEXT(B97,"mmm") -> Jan | D97: =TEXT(B97,"ddd") -> Tue | E97: Kolkata | F97: Chinese | G97: New | H97: UPI | I97: 438 | J97: 94 | K97: 30 | L97: =IF(O97="Delivered",I97-J97+K97,0) -> 374 | M97: 40 | N97: 3.9 | O97: Delivered
A98: FD100018 | B98: 45686 | C98: =TEXT(B98,"mmm") -> Jan | D98: =TEXT(B98,"ddd") -> Wed | E98: Kolkata | F98: North Indian | G98: New | H98: Cash on Delivery | I98: 540 | J98: 0 | K98: 0 | L98: =IF(O98="Delivered",I98-J98+K98,0) -> 540 | M98: 30 | N98: 3.8 | O98: Delivered
A99: FD101444 | B99: 45686 | C99: =TEXT(B99,"mmm") -> Jan | D99: =TEXT(B99,"ddd") -> Wed | E99: Mumbai | F99: Healthy | G99: Returning | H99: UPI | I99: 565 | J99: 0 | K99: 0 | L99: =IF(O99="Delivered",I99-J99+K99,0) -> 565 | M99: 43 | N99: 4.5 | O99: Delivered
A100: FD100259 | B100: 45687 | C100: =TEXT(B100,"mmm") -> Jan | D100: =TEXT(B100,"ddd") -> Thu | E100: Pune | F100: Pizza | G100: New | H100: Credit Card | I100: 450 | J100: 103 | K100: 40 | L100: =IF(O100="Delivered",I100-J100+K100,0) -> 387 | M100: 33 | N100: 4.7 | O100: Delivered
A101: FD100681 | B101: 45687 | C101: =TEXT(B101,"mmm") -> Jan | D101: =TEXT(B101,"ddd") -> Thu | E101: Chennai | F101: Chinese | G101: Returning | H101: Debit Card | I101: 419 | J101: 91 | K101: 40 | L101: =IF(O101="Delivered",I101-J101+K101,0) -> 0 | O101: Cancelled
A102: FD100728 | B102: 45687 | C102: =TEXT(B102,"mmm") -> Jan | D102: =TEXT(B102,"ddd") -> Thu | E102: Mumbai | F102: Biryani | G102: New | H102: UPI | I102: 318 | J102: 54 | K102: 20 | L102: =IF(O102="Delivered",I102-J102+K102,0) -> 284 | M102: 35 | N102: 4.4 | O102: Delivered
A103: FD101220 | B103: 45687 | C103: =TEXT(B103,"mmm") -> Jan | D103: =TEXT(B103,"ddd") -> Thu | E103: Bengaluru | F103: Chinese | G103: New | H103: UPI | I103: 414 | J103: 55 | K103: 20 | L103: =IF(O103="Delivered",I103-J103+K103,0) -> 379 | M103: 43 | N103: 4.3 | O103: Delivered
A104: FD101482 | B104: 45687 | C104: =TEXT(B104,"mmm") -> Jan | D104: =TEXT(B104,"ddd") -> Thu | E104: Delhi | F104: Pizza | G104: Returning | H104: Wallet | I104: 672 | J104: 0 | K104: 0 | L104: =IF(O104="Delivered",I104-J104+K104,0) -> 672 | M104: 35 | N104: 3.3 | O104: Delivered
A105: FD101116 | B105: 45688 | C105: =TEXT(B105,"mmm") -> Jan | D105: =TEXT(B105,"ddd") -> Fri | E105: Bengaluru | F105: Biryani | G105: New | H105: Wallet | I105: 312 | J105: 73 | K105: 20 | L105: =IF(O105="Delivered",I105-J105+K105,0) -> 259 | M105: 36 | N105: 4.4 | O105: Delivered
A106: FD101156 | B106: 45688 | C106: =TEXT(B106,"mmm") -> Jan | D106: =TEXT(B106,"ddd") -> Fri | E106: Kolkata | F106: North Indian | G106: New | H106: Cash on Delivery | I106: 620 | J106: 130 | K106: 0 | L106: =IF(O106="Delivered",I106-J106+K106,0) -> 490 | M106: 31 | N106: 4.9 | O106: Delivered
A107: FD100511 | B107: 45689 | C107: =TEXT(B107,"mmm") -> Feb | D107: =TEXT(B107,"ddd") -> Sat | E107: Mumbai | F107: Desserts | G107: New | H107: Cash on Delivery | I107: 479 | J107: 0 | K107: 45 | L107: =IF(O107="Delivered",I107-J107+K107,0) -> 524 | M107: 38 | N107: 4.2 | O107: Delivered
A108: FD100917 | B108: 45689 | C108: =TEXT(B108,"mmm") -> Feb | D108: =TEXT(B108,"ddd") -> Sat | E108: Delhi | F108: Fast Food | G108: New | H108: UPI | I108: 335 | J108: 57 | K108: 20 | L108: =IF(O108="Delivered",I108-J108+K108,0) -> 298 | M108: 24 | N108: 4.4 | O108: Delivered
A109: FD100794 | B109: 45692 | C109: =TEXT(B109,"mmm") -> Feb | D109: =TEXT(B109,"ddd") -> Tue | E109: Delhi | F109: North Indian | G109: Returning | H109: Debit Card | I109: 573 | J109: 0 | K109: 0 | L109: =IF(O109="Delivered",I109-J109+K109,0) -> 0 | O109: Cancelled
A110: FD101428 | B110: 45692 | C110: =TEXT(B110,"mmm") -> Feb | D110: =TEXT(B110,"ddd") -> Tue | E110: Bengaluru | F110: North Indian | G110: Returning | H110: UPI | I110: 420 | J110: 0 | K110: 30 | L110: =IF(O110="Delivered",I110-J110+K110,0) -> 450 | M110: 49 | N110: 3.8 | O110: Delivered
A111: FD100548 | B111: 45693 | C111: =TEXT(B111,"mmm") -> Feb | D111: =TEXT(B111,"ddd") -> Wed | E111: Bengaluru | F111: Desserts | G111: Returning | H111: Credit Card | I111: 310 | J111: 0 | K111: 20 | L111: =IF(O111="Delivered",I111-J111+K111,0) -> 330 | M111: 43 | N111: 4.3 | O111: Delivered
A112: FD101376 | B112: 45693 | C112: =TEXT(B112,"mmm") -> Feb | D112: =TEXT(B112,"ddd") -> Wed | E112: Delhi | F112: North Indian | G112: Returning | H112: UPI | I112: 491 | J112: 0 | K112: 30 | L112: =IF(O112="Delivered",I112-J112+K112,0) -> 521 | M112: 36 | N112: 4.2 | O112: Delivered
A113: FD100140 | B113: 45694 | C113: =TEXT(B113,"mmm") -> Feb | D113: =TEXT(B113,"ddd") -> Thu | E113: Hyderabad | F113: Fast Food | G113: New | H113: Credit Card | I113: 360 | J113: 0 | K113: 40 | L113: =IF(O113="Delivered",I113-J113+K113,0) -> 400 | M113: 31 | N113: 4 | O113: Delivered
A114: FD100123 | B114: 45695 | C114: =TEXT(B114,"mmm") -> Feb | D114: =TEXT(B114,"ddd") -> Fri | E114: Chennai | F114: Biryani | G114: Returning | H114: Cash on Delivery | I114: 588 | J114: 0 | K114: 0 | L114: =IF(O114="Delivered",I114-J114+K114,0) -> 588 | M114: 46 | N114: 3.1 | O114: Delivered
A115: FD100339 | B115: 45695 | C115: =TEXT(B115,"mmm") -> Feb | D115: =TEXT(B115,"ddd") -> Fri | E115: Chennai | F115: Biryani | G115: New | H115: UPI | I115: 538 | J115: 63 | K115: 0 | L115: =IF(O115="Delivered",I115-J115+K115,0) -> 475 | M115: 37 | N115: 3.4 | O115: Delivered
A116: FD100561 | B116: 45695 | C116: =TEXT(B116,"mmm") -> Feb | D116: =TEXT(B116,"ddd") -> Fri | E116: Kolkata | F116: Chinese | G116: New | H116: Credit Card | I116: 296 | J116: 72 | K116: 30 | L116: =IF(O116="Delivered",I116-J116+K116,0) -> 254 | M116: 31 | N116: 4.2 | O116: Delivered
A117: FD100628 | B117: 45695 | C117: =TEXT(B117,"mmm") -> Feb | D117: =TEXT(B117,"ddd") -> Fri | E117: Delhi | F117: Chinese | G117: New | H117: Debit Card | I117: 415 | J117: 44 | K117: 45 | L117: =IF(O117="Delivered",I117-J117+K117,0) -> 416 | M117: 32 | N117: 4.5 | O117: Delivered
A118: FD100664 | B118: 45695 | C118: =TEXT(B118,"mmm") -> Feb | D118: =TEXT(B118,"ddd") -> Fri | E118: Bengaluru | F118: Chinese | G118: Returning | H118: Cash on Delivery | I118: 474 | J118: 0 | K118: 30 | L118: =IF(O118="Delivered",I118-J118+K118,0) -> 504 | M118: 33 | N118: 4.8 | O118: Delivered
...

Sheet Pivot Tables
A1: PIVOT-STYLE SUMMARY TABLES (live formulas on tblOrders – respond to Dashboard filters)
A3: City filter | B3: =IF(Dashboard!$C$4="All","*",Dashboard!$C$4) -> * | C3: ← criteria driven by Dashboard dropdowns ('*' = All)
A4: Cuisine filter | B4: =IF(Dashboard!$C$5="All","*",Dashboard!$C$5) -> *
A5: Customer filter | B5: =IF(Dashboard!$C$6="All","*",Dashboard!$C$6) -> *
A7: PIVOT 1 – Sales by City
A8: City | B8: Orders | C8: Net Revenue (₹) | D8: Avg Order Value (₹) | E8: Avg Delivery Time (min) | F8: Avg Rating
A9: Mumbai | B9: =COUNTIFS('Cleaned Data'!$E$2:$E$1489,$B$3,'Cleaned Data'!$F$2:$F$1489,$B$4,'Cleaned Data'!$G$2:$G$1489,$B$5,'Cleaned Data'!$O$2:$O$1489,"Delivered",'Cleaned Data'!$E$2:$E$1489,$A9) -> 276 | C9: =SUMIFS('Cleaned Data'!$L$2:$L$1489,'Cleaned Data'!$E$2:$E$1489,$B$3,'Cleaned Data'!$F$2:$F$1489,$B$4,'Cleaned Data'!$G$2:$G$1489,$B$5,'Cleaned Data'!$O$2:$O$1489,"Delivered",'Cleaned Data'!$E$2:$E$1489,$A9) -> 121927 | D9: =IFERROR(C9/B9,0) -> 441.76449 | E9: =IFERROR(AVERAGEIFS('Cleaned Data'!$M$2:$M$1489,'Cleaned Data'!$E$2:$E$1489,$B$3,'Cleaned Data'!$F$2:$F$1489,$B$4,'Cleaned Data'!$G$2:$G$1489,$B$5,'Cleaned Data'!$O$2:$O$1489,"Delivered",'Cleaned Data'!$E$2:$E$1489,$A9),0) -> 37.985507 | F9: =IFERROR(AVERAGEIFS('Cleaned Data'!$N$2:$N$1489,'Cleaned Data'!$E$2:$E$1489,$B$3,'Cleaned Data'!$F$2:$F$1489,$B$4,'Cleaned Data'!$G$2:$G$1489,$B$5,'Cleaned Data'!$O$2:$O$1489,"Delivered",'Cleaned Data'!$E$2:$E$1489,$A9),0) -> 4.2876448
A10: Delhi | B10: =COUNTIFS('Cleaned Data'!$E$2:$E$1489,$B$3,'Cleaned Data'!$F$2:$F$1489,$B$4,'Cleaned Data'!$G$2:$G$1489,$B$5,'Cleaned Data'!$O$2:$O$1489,"Delivered",'Cleaned Data'!$E$2:$E$1489,$A10) -> 280 | C10: =SUMIFS('Cleaned Data'!$L$2:$L$1489,'Cleaned Data'!$E$2:$E$1489,$B$3,'Cleaned Data'!$F$2:$F$1489,$B$4,'Cleaned Data'!$G$2:$G$1489,$B$5,'Cleaned Data'!$O$2:$O$1489,"Delivered",'Cleaned Data'!$E$2:$E$1489,$A10) -> 128254 | D10: =IFERROR(C10/B10,0) -> 458.05 | E10: =IFERROR(AVERAGEIFS('Cleaned Data'!$M$2:$M$1489,'Cleaned Data'!$E$2:$E$1489,$B$3,'Cleaned Data'!$F$2:$F$1489,$B$4,'Cleaned Data'!$G$2:$G$1489,$B$5,'Cleaned Data'!$O$2:$O$1489,"Delivered",'Cleaned Data'!$E$2:$E$1489,$A10),0) -> 36.107143 | F10: =IFERROR(AVERAGEIFS('Cleaned Data'!$N$2:$N$1489,'Cleaned Data'!$E$2:$E$1489,$B$3,'Cleaned Data'!$F$2:$F$1489,$B$4,'Cleaned Data'!$G$2:$G$1489,$B$5,'Cleaned Data'!$O$2:$O$1489,"Delivered",'Cleaned Data'!$E$2:$E$1489,$A10),0) -> 4.2350943
A11: Bengaluru | B11: =COUNTIFS('Cleaned Data'!$E$2:$E$1489,$B$3,'Cleaned Data'!$F$2:$F$1489,$B$4,'Cleaned Data'!$G$2:$G$1489,$B$5,'Cleaned Data'!$O$2:$O$1489,"Delivered",'Cleaned Data'!$E$2:$E$1489,$A11) -> 319 | C11: =SUMIFS('Cleaned Data'!$L$2:$L$1489,'Cleaned Data'!$E$2:$E$1489,$B$3,'Cleaned Data'!$F$2:$F$1489,$B$4,'Cleaned Data'!$G$2:$G$1489,$B$5,'Cleaned Data'!$O$2:$O$1489,"Delivered",'Cleaned Data'!$E$2:$E$1489,$A11) -> 141596 | D11: =IFERROR(C11/B11,0) -> 443.87461 | E11: =IFERROR(AVERAGEIFS('Cleaned Data'!$M$2:$M$1489,'Cleaned Data'!$E$2:$E$1489,$B$3,'Cleaned Data'!$F$2:$F$1489,$B$4,'Cleaned Data'!$G$2:$G$1489,$B$5,'Cleaned Data'!$O$2:$O$1489,"Delivered",'Cleaned Data'!$E$2:$E$1489,$A11),0) -> 41.912226 | F11: =IFERROR(AVERAGEIFS('Cleaned Data'!$N$2:$N$1489,'Cleaned Data'!$E$2:$E$1489,$B$3,'Cleaned Data'!$F$2:$F$1489,$B$4,'Cleaned Data'!$G$2:$G$1489,$B$5,'Cleaned Data'!$O$2:$O$1489,"Delivered",'Cleaned Data'!$E$2:$E$1489,$A11),0) -> 4.1192691
A12: Hyderabad | B12: =COUNTIFS('Cleaned Data'!$E$2:$E$1489,$B$3,'Cleaned Data'!$F$2:$F$1489,$B$4,'Cleaned Data'!$G$2:$G$1489,$B$5,'Cleaned Data'!$O$2:$O$1489,"Delivered",'Cleaned Data'!$E$2:$E$1489,$A12) -> 185 | C12: =SUMIFS('Cleaned Data'!$L$2:$L$1489,'Cleaned Data'!$E$2:$E$1489,$B$3,'Cleaned Data'!$F$2:$F$1489,$B$4,'Cleaned Data'!$G$2:$G$1489,$B$5,'Cleaned Data'!$O$2:$O$1489,"Delivered",'Cleaned Data'!$E$2:$E$1489,$A12) -> 82386 | D12: =IFERROR(C12/B12,0) -> 445.32973 | E12: =IFERROR(AVERAGEIFS('Cleaned Data'!$M$2:$M$1489,'Cleaned Data'!$E$2:$E$1489,$B$3,'Cleaned Data'!$F$2:$F$1489,$B$4,'Cleaned Data'!$G$2:$G$1489,$B$5,'Cleaned Data'!$O$2:$O$1489,"Delivered",'Cleaned Data'!$E$2:$E$1489,$A12),0) -> 32.881081 | F12: =IFERROR(AVERAGEIFS('Cleaned Data'!$N$2:$N$1489,'Cleaned Data'!$E$2:$E$1489,$B$3,'Cleaned Data'!$F$2:$F$1489,$B$4,'Cleaned Data'!$G$2:$G$1489,$B$5,'Cleaned Data'!$O$2:$O$1489,"Delivered",'Cleaned Data'!$E$2:$E$1489,$A12),0) -> 4.3011364
A13: Chennai | B13: =COUNTIFS('Cleaned Data'!$E$2:$E$1489,$B$3,'Cleaned Data'!$F$2:$F$1489,$B$4,'Cleaned Data'!$G$2:$G$1489,$B$5,'Cleaned Data'!$O$2:$O$1489,"Delivered",'Cleaned Data'!$E$2:$E$1489,$A13) -> 109 | C13: =SUMIFS('Cleaned Data'!$L$2:$L$1489,'Cleaned Data'!$E$2:$E$1489,$B$3,'Cleaned Data'!$F$2:$F$1489,$B$4,'Cleaned Data'!$G$2:$G$1489,$B$5,'Cleaned Data'!$O$2:$O$1489,"Delivered",'Cleaned Data'!$E$2:$E$1489,$A13) -> 48378 | D13: =IFERROR(C13/B13,0) -> 443.83486 | E13: =IFERROR(AVERAGEIFS('Cleaned Data'!$M$2:$M$1489,'Cleaned Data'!$E$2:$E$1489,$B$3,'Cleaned Data'!$F$2:$F$1489,$B$4,'Cleaned Data'!$G$2:$G$1489,$B$5,'Cleaned Data'!$O$2:$O$1489,"Delivered",'Cleaned Data'!$E$2:$E$1489,$A13),0) -> 31.385321 | F13: =IFERROR(AVERAGEIFS('Cleaned Data'!$N$2:$N$1489,'Cleaned Data'!$E$2:$E$1489,$B$3,'Cleaned Data'!$F$2:$F$1489,$B$4,'Cleaned Data'!$G$2:$G$1489,$B$5,'Cleaned Data'!$O$2:$O$1489,"Delivered",'Cleaned Data'!$E$2:$E$1489,$A13),0) -> 4.3773196
A14: Pune | B14: =COUNTIFS('Cleaned Data'!$E$2:$E$1489,$B$3,'Cleaned Data'!$F$2:$F$1489,$B$4,'Cleaned Data'!$G$2:$G$1489,$B$5,'Cleaned Data'!$O$2:$O$1489,"Delivered",'Cleaned Data'!$E$2:$E$1489,$A14) -> 103 | C14: =SUMIFS('Cleaned Data'!$L$2:$L$1489,'Cleaned Data'!$E$2:$E$1489,$B$3,'Cleaned Data'!$F$2:$F$1489,$B$4,'Cleaned Data'!$G$2:$G$1489,$B$5,'Cleaned Data'!$O$2:$O$1489,"Delivered",'Cleaned Data'!$E$2:$E$1489,$A14) -> 44264 | D14: =IFERROR(C14/B14,0) -> 429.74757 | E14: =IFERROR(AVERAGEIFS('Cleaned Data'!$M$2:$M$1489,'Cleaned Data'!$E$2:$E$1489,$B$3,'Cleaned Data'!$F$2:$F$1489,$B$4,'Cleaned Data'!$G$2:$G$1489,$B$5,'Cleaned Data'!$O$2:$O$1489,"Delivered",'Cleaned Data'!$E$2:$E$1489,$A14),0) -> 29.679612 | F14: =IFERROR(AVERAGEIFS('Cleaned Data'!$N$2:$N$1489,'Cleaned Data'!$E$2:$E$1489,$B$3,'Cleaned Data'!$F$2:$F$1489,$B$4,'Cleaned Data'!$G$2:$G$1489,$B$5,'Cleaned Data'!$O$2:$O$1489,"Delivered",'Cleaned Data'!$E$2:$E$1489,$A14),0) -> 4.3514851
A15: Kolkata | B15: =COUNTIFS('Cleaned Data'!$E$2:$E$1489,$B$3,'Cleaned Data'!$F$2:$F$1489,$B$4,'Cleaned Data'!$G$2:$G$1489,$B$5,'Cleaned Data'!$O$2:$O$1489,"Delivered",'Cleaned Data'!$E$2:$E$1489,$A15) -> 75 | C15: =SUMIFS('Cleaned Data'!$L$2:$L$1489,'Cleaned Data'!$E$2:$E$1489,$B$3,'Cleaned Data'!$F$2:$F$1489,$B$4,'Cleaned Data'!$G$2:$G$1489,$B$5,'Cleaned Data'!$O$2:$O$1489,"Delivered",'Cleaned Data'!$E$2:$E$1489,$A15) -> 32648 | D15: =IFERROR(C15/B15,0) -> 435.30667 | E15: =IFERROR(AVERAGEIFS('Cleaned Data'!$M$2:$M$1489,'Cleaned Data'!$E$2:$E$1489,$B$3,'Cleaned Data'!$F$2:$F$1489,$B$4,'Cleaned Data'!$G$2:$G$1489,$B$5,'Cleaned Data'!$O$2:$O$1489,"Delivered",'Cleaned Data'!$E$2:$E$1489,$A15),0) -> 34.826667 | F15: =IFERROR(AVERAGEIFS('Cleaned Data'!$N$2:$N$1489,'Cleaned Data'!$E$2:$E$1489,$B$3,'Cleaned Data'!$F$2:$F$1489,$B$4,'Cleaned Data'!$G$2:$G$1489,$B$5,'Cleaned Data'!$O$2:$O$1489,"Delivered",'Cleaned Data'!$E$2:$E$1489,$A15),0) -> 4.2690141
A16: Ahmedabad | B16: =COUNTIFS('Cleaned Data'!$E$2:$E$1489,$B$3,'Cleaned Data'!$F$2:$F$1489,$B$4,'Cleaned Data'!$G$2:$G$1489,$B$5,'Cleaned Data'!$O$2:$O$1489,"Delivered",'Cleaned Data'!$E$2:$E$1489,$A16) -> 58 | C16: =SUMIFS('Cleaned Data'!$L$2:$L$1489,'Cleaned Data'!$E$2:$E$1489,$B$3,'Cleaned Data'!$F$2:$F$1489,$B$4,'Cleaned Data'!$G$2:$G$1489,$B$5,'Cleaned Data'!$O$2:$O$1489,"Delivered",'Cleaned Data'!$E$2:$E$1489,$A16) -> 25818 | D16: =IFERROR(C16/B16,0) -> 445.13793 | E16: =IFERROR(AVERAGEIFS('Cleaned Data'!$M$2:$M$1489,'Cleaned Data'!$E$2:$E$1489,$B$3,'Cleaned Data'!$F$2:$F$1489,$B$4,'Cleaned Data'!$G$2:$G$1489,$B$5,'Cleaned Data'!$O$2:$O$1489,"Delivered",'Cleaned Data'!$E$2:$E$1489,$A16),0) -> 27.810345 | F16: =IFERROR(AVERAGEIFS('Cleaned Data'!$N$2:$N$1489,'Cleaned Data'!$E$2:$E$1489,$B$3,'Cleaned Data'!$F$2:$F$1489,$B$4,'Cleaned Data'!$G$2:$G$1489,$B$5,'Cleaned Data'!$O$2:$O$1489,"Delivered",'Cleaned Data'!$E$2:$E$1489,$A16),0) -> 4.454386
A17: Grand Total | B17: =SUM(B9:B16) -> 1405 | C17: =SUM(C9:C16) -> 625271 | D17: =IFERROR(C17/B17,0) -> 445.03274 | E17: =IFERROR(AVERAGE(E9:E16),0) -> 34.073488 | F17: =IFERROR(AVERAGE(F9:F16),0) -> 4.2994187
A20: PIVOT 2 – Sales by Cuisine
A21: Cuisine | B21: Orders | C21: Net Revenue (₹) | D21: Avg Order Value (₹)
A22: North Indian | B22: =COUNTIFS('Cleaned Data'!$E$2:$E$1489,$B$3,'Cleaned Data'!$F$2:$F$1489,$B$4,'Cleaned Data'!$G$2:$G$1489,$B$5,'Cleaned Data'!$O$2:$O$1489,"Delivered",'Cleaned Data'!$F$2:$F$1489,$A22) -> 293 | C22: =SUMIFS('Cleaned Data'!$L$2:$L$1489,'Cleaned Data'!$E$2:$E$1489,$B$3,'Cleaned Data'!$F$2:$F$1489,$B$4,'Cleaned Data'!$G$2:$G$1489,$B$5,'Cleaned Data'!$O$2:$O$1489,"Delivered",'Cleaned Data'!$F$2:$F$1489,$A22) -> 139535 | D22: =IFERROR(C22/B22,0) -> 476.22867
A23: Biryani | B23: =COUNTIFS('Cleaned Data'!$E$2:$E$1489,$B$3,'Cleaned Data'!$F$2:$F$1489,$B$4,'Cleaned Data'!$G$2:$G$1489,$B$5,'Cleaned Data'!$O$2:$O$1489,"Delivered",'Cleaned Data'!$F$2:$F$1489,$A23) -> 240 | C23: =SUMIFS('Cleaned Data'!$L$2:$L$1489,'Cleaned Data'!$E$2:$E$1489,$B$3,'Cleaned Data'!$F$2:$F$1489,$B$4,'Cleaned Data'!$G$2:$G$1489,$B$5,'Cleaned Data'!$O$2:$O$1489,"Delivered",'Cleaned Data'!$F$2:$F$1489,$A23) -> 107801 | D23: =IFERROR(C23/B23,0) -> 449.17083
A24: Fast Food | B24: =COUNTIFS('Cleaned Data'!$E$2:$E$1489,$B$3,'Cleaned Data'!$F$2:$F$1489,$B$4,'Cleaned Data'!$G$2:$G$1489,$B$5,'Cleaned Data'!$O$2:$O$1489,"Delivered",'Cleaned Data'!$F$2:$F$1489,$A24) -> 219 | C24: =SUMIFS('Cleaned Data'!$L$2:$L$1489,'Cleaned Data'!$E$2:$E$1489,$B$3,'Cleaned Data'!$F$2:$F$1489,$B$4,'Cleaned Data'!$G$2:$G$1489,$B$5,'Cleaned Data'!$O$2:$O$1489,"Delivered",'Cleaned Data'!$F$2:$F$1489,$A24) -> 83515 | D24: =IFERROR(C24/B24,0) -> 381.34703
A25: Pizza | B25: =COUNTIFS('Cleaned Data'!$E$2:$E$1489,$B$3,'Cleaned Data'!$F$2:$F$1489,$B$4,'Cleaned Data'!$G$2:$G$1489,$B$5,'Cleaned Data'!$O$2:$O$1489,"Delivered",'Cleaned Data'!$F$2:$F$1489,$A25) -> 189 | C25: =SUMIFS('Cleaned Data'!$L$2:$L$1489,'Cleaned Data'!$E$2:$E$1489,$B$3,'Cleaned Data'!$F$2:$F$1489,$B$4,'Cleaned Data'!$G$2:$G$1489,$B$5,'Cleaned Data'!$O$2:$O$1489,"Delivered",'Cleaned Data'!$F$2:$F$1489,$A25) -> 109913 | D25: =IFERROR(C25/B25,0) -> 581.55026
A26: Chinese | B26: =COUNTIFS('Cleaned Data'!$E$2:$E$1489,$B$3,'Cleaned Data'!$F$2:$F$1489,$B$4,'Cleaned Data'!$G$2:$G$1489,$B$5,'Cleaned Data'!$O$2:$O$1489,"Delivered",'Cleaned Data'!$F$2:$F$1489,$A26) -> 173 | C26: =SUMIFS('Cleaned Data'!$L$2:$L$1489,'Cleaned Data'!$E$2:$E$1489,$B$3,'Cleaned Data'!$F$2:$F$1489,$B$4,'Cleaned Data'!$G$2:$G$1489,$B$5,'Cleaned Data'!$O$2:$O$1489,"Delivered",'Cleaned Data'!$F$2:$F$1489,$A26) -> 74244 | D26: =IFERROR(C26/B26,0) -> 429.15607
A27: South Indian | B27: =COUNTIFS('Cleaned Data'!$E$2:$E$1489,$B$3,'Cleaned Data'!$F$2:$F$1489,$B$4,'Cleaned Data'!$G$2:$G$1489,$B$5,'Cleaned Data'!$O$2:$O$1489,"Delivered",'Cleaned Data'!$F$2:$F$1489,$A27) -> 147 | C27: =SUMIFS('Cleaned Data'!$L$2:$L$1489,'Cleaned Data'!$E$2:$E$1489,$B$3,'Cleaned Data'!$F$2:$F$1489,$B$4,'Cleaned Data'!$G$2:$G$1489,$B$5,'Cleaned Data'!$O$2:$O$1489,"Delivered",'Cleaned Data'!$F$2:$F$1489,$A27) -> 47916 | D27: =IFERROR(C27/B27,0) -> 325.95918
A28: Healthy | B28: =COUNTIFS('Cleaned Data'!$E$2:$E$1489,$B$3,'Cleaned Data'!$F$2:$F$1489,$B$4,'Cleaned Data'!$G$2:$G$1489,$B$5,'Cleaned Data'!$O$2:$O$1489,"Delivered",'Cleaned Data'!$F$2:$F$1489,$A28) -> 76 | C28: =SUMIFS('Cleaned Data'!$L$2:$L$1489,'Cleaned Data'!$E$2:$E$1489,$B$3,'Cleaned Data'!$F$2:$F$1489,$B$4,'Cleaned Data'!$G$2:$G$1489,$B$5,'Cleaned Data'!$O$2:$O$1489,"Delivered",'Cleaned Data'!$F$2:$F$1489,$A28) -> 36344 | D28: =IFERROR(C28/B28,0) -> 478.21053
A29: Desserts | B29: =COUNTIFS('Cleaned Data'!$E$2:$E$1489,$B$3,'Cleaned Data'!$F$2:$F$1489,$B$4,'Cleaned Data'!$G$2:$G$1489,$B$5,'Cleaned Data'!$O$2:$O$1489,"Delivered",'Cleaned Data'!$F$2:$F$1489,$A29) -> 68 | C29: =SUMIFS('Cleaned Data'!$L$2:$L$1489,'Cleaned Data'!$E$2:$E$1489,$B$3,'Cleaned Data'!$F$2:$F$1489,$B$4,'Cleaned Data'!$G$2:$G$1489,$B$5,'Cleaned Data'!$O$2:$O$1489,"Delivered",'Cleaned Data'!$F$2:$F$1489,$A29) -> 26003 | D29: =IFERROR(C29/B29,0) -> 382.39706
A30: Grand Total | B30: =SUM(B22:B29) -> 1405 | C30: =SUM(C22:C29) -> 625271 | D30: =IFERROR(C30/B30,0) -> 445.03274
A33: PIVOT 3 – Monthly Trend
A34: Month | B34: Orders | C34: Net Revenue (₹) | D34: Avg Order Value (₹)
A35: Jan | B35: =COUNTIFS('Cleaned Data'!$E$2:$E$1489,$B$3,'Cleaned Data'!$F$2:$F$1489,$B$4,'Cleaned Data'!$G$2:$G$1489,$B$5,'Cleaned Data'!$O$2:$O$1489,"Delivered",'Cleaned Data'!$C$2:$C$1489,$A35) -> 99 | C35: =SUMIFS('Cleaned Data'!$L$2:$L$1489,'Cleaned Data'!$E$2:$E$1489,$B$3,'Cleaned Data'!$F$2:$F$1489,$B$4,'Cleaned Data'!$G$2:$G$1489,$B$5,'Cleaned Data'!$O$2:$O$1489,"Delivered",'Cleaned Data'!$C$2:$C$1489,$A35) -> 43004 | D35: =IFERROR(C35/B35,0) -> 434.38384
A36: Feb | B36: =COUNTIFS('Cleaned Data'!$E$2:$E$1489,$B$3,'Cleaned Data'!$F$2:$F$1489,$B$4,'Cleaned Data'!$G$2:$G$1489,$B$5,'Cleaned Data'!$O$2:$O$1489,"Delivered",'Cleaned Data'!$C$2:$C$1489,$A36) -> 100 | C36: =SUMIFS('Cleaned Data'!$L$2:$L$1489,'Cleaned Data'!$E$2:$E$1489,$B$3,'Cleaned Data'!$F$2:$F$1489,$B$4,'Cleaned Data'!$G$2:$G$1489,$B$5,'Cleaned Data'!$O$2:$O$1489,"Delivered",'Cleaned Data'!$C$2:$C$1489,$A36) -> 43954 | D36: =IFERROR(C36/B36,0) -> 439.54
A37: Mar | B37: =COUNTIFS('Cleaned Data'!$E$2:$E$1489,$B$3,'Cleaned Data'!$F$2:$F$1489,$B$4,'Cleaned Data'!$G$2:$G$1489,$B$5,'Cleaned Data'!$O$2:$O$1489,"Delivered",'Cleaned Data'!$C$2:$C$1489,$A37) -> 118 | C37: =SUMIFS('Cleaned Data'!$L$2:$L$1489,'Cleaned Data'!$E$2:$E$1489,$B$3,'Cleaned Data'!$F$2:$F$1489,$B$4,'Cleaned Data'!$G$2:$G$1489,$B$5,'Cleaned Data'!$O$2:$O$1489,"Delivered",'Cleaned Data'!$C$2:$C$1489,$A37) -> 54175 | D37: =IFERROR(C37/B37,0) -> 459.11017
A38: Apr | B38: =COUNTIFS('Cleaned Data'!$E$2:$E$1489,$B$3,'Cleaned Data'!$F$2:$F$1489,$B$4,'Cleaned Data'!$G$2:$G$1489,$B$5,'Cleaned Data'!$O$2:$O$1489,"Delivered",'Cleaned Data'!$C$2:$C$1489,$A38) -> 87 | C38: =SUMIFS('Cleaned Data'!$L$2:$L$1489,'Cleaned Data'!$E$2:$E$1489,$B$3,'Cleaned Data'!$F$2:$F$1489,$B$4,'Cleaned Data'!$G$2:$G$1489,$B$5,'Cleaned Data'!$O$2:$O$1489,"Delivered",'Cleaned Data'!$C$2:$C$1489,$A38) -> 39431 | D38: =IFERROR(C38/B38,0) -> 453.22989
A39: May | B39: =COUNTIFS('Cleaned Data'!$E$2:$E$1489,$B$3,'Cleaned Data'!$F$2:$F$1489,$B$4,'Cleaned Data'!$G$2:$G$1489,$B$5,'Cleaned Data'!$O$2:$O$1489,"Delivered",'Cleaned Data'!$C$2:$C$1489,$A39) -> 106 | C39: =SUMIFS('Cleaned Data'!$L$2:$L$1489,'Cleaned Data'!$E$2:$E$1489,$B$3,'Cleaned Data'!$F$2:$F$1489,$B$4,'Cleaned Data'!$G$2:$G$1489,$B$5,'Cleaned Data'!$O$2:$O$1489,"Delivered",'Cleaned Data'!$C$2:$C$1489,$A39) -> 47501 | D39: =IFERROR(C39/B39,0) -> 448.12264
A40: Jun | B40: =COUNTIFS('Cleaned Data'!$E$2:$E$1489,$B$3,'Cleaned Data'!$F$2:$F$1489,$B$4,'Cleaned Data'!$G$2:$G$1489,$B$5,'Cleaned Data'!$O$2:$O$1489,"Delivered",'Cleaned Data'!$C$2:$C$1489,$A40) -> 122 | C40: =SUMIFS('Cleaned Data'!$L$2:$L$1489,'Cleaned Data'!$E$2:$E$1489,$B$3,'Cleaned Data'!$F$2:$F$1489,$B$4,'Cleaned Data'!$G$2:$G$1489,$B$5,'Cleaned Data'!$O$2:$O$1489,"Delivered",'Cleaned Data'!$C$2:$C$1489,$A40) -> 52426 | D40: =IFERROR(C40/B40,0) -> 429.72131
A41: Jul | B41: =COUNTIFS('Cleaned Data'!$E$2:$E$1489,$B$3,'Cleaned Data'!$F$2:$F$1489,$B$4,'Cleaned Data'!$G$2:$G$1489,$B$5,'Cleaned Data'!$O$2:$O$1489,"Delivered",'Cleaned Data'!$C$2:$C$1489,$A41) -> 123 | C41: =SUMIFS('Cleaned Data'!$L$2:$L$1489,'Cleaned Data'!$E$2:$E$1489,$B$3,'Cleaned Data'!$F$2:$F$1489,$B$4,'Cleaned Data'!$G$2:$G$1489,$B$5,'Cleaned Data'!$O$2:$O$1489,"Delivered",'Cleaned Data'!$C$2:$C$1489,$A41) -> 55728 | D41: =IFERROR(C41/B41,0) -> 453.07317
A42: Aug | B42: =COUNTIFS('Cleaned Data'!$E$2:$E$1489,$B$3,'Cleaned Data'!$F$2:$F$1489,$B$4,'Cleaned Data'!$G$2:$G$1489,$B$5,'Cleaned Data'!$O$2:$O$1489,"Delivered",'Cleaned Data'!$C$2:$C$1489,$A42) -> 126 | C42: =SUMIFS('Cleaned Data'!$L$2:$L$1489,'Cleaned Data'!$E$2:$E$1489,$B$3,'Cleaned Data'!$F$2:$F$1489,$B$4,'Cleaned Data'!$G$2:$G$1489,$B$5,'Cleaned Data'!$O$2:$O$1489,"Delivered",'Cleaned Data'!$C$2:$C$1489,$A42) -> 57779 | D42: =IFERROR(C42/B42,0) -> 458.56349
A43: Sep | B43: =COUNTIFS('Cleaned Data'!$E$2:$E$1489,$B$3,'Cleaned Data'!$F$2:$F$1489,$B$4,'Cleaned Data'!$G$2:$G$1489,$B$5,'Cleaned Data'!$O$2:$O$1489,"Delivered",'Cleaned Data'!$C$2:$C$1489,$A43) -> 124 | C43: =SUMIFS('Cleaned Data'!$L$2:$L$1489,'Cleaned Data'!$E$2:$E$1489,$B$3,'Cleaned Data'!$F$2:$F$1489,$B$4,'Cleaned Data'!$G$2:$G$1489,$B$5,'Cleaned Data'!$O$2:$O$1489,"Delivered",'Cleaned Data'!$C$2:$C$1489,$A43) -> 54456 | D43: =IFERROR(C43/B43,0) -> 439.16129
A44: Oct | B44: =COUNTIFS('Cleaned Data'!$E$2:$E$1489,$B$3,'Cleaned Data'!$F$2:$F$1489,$B$4,'Cleaned Data'!$G$2:$G$1489,$B$5,'Cleaned Data'!$O$2:$O$1489,"Delivered",'Cleaned Data'!$C$2:$C$1489,$A44) -> 130 | C44: =SUMIFS('Cleaned Data'!$L$2:$L$1489,'Cleaned Data'!$E$2:$E$1489,$B$3,'Cleaned Data'!$F$2:$F$1489,$B$4,'Cleaned Data'!$G$2:$G$1489,$B$5,'Cleaned Data'!$O$2:$O$1489,"Delivered",'Cleaned Data'!$C$2:$C$1489,$A44) -> 58826 | D44: =IFERROR(C44/B44,0) -> 452.50769
A45: Nov | B45: =COUNTIFS('Cleaned Data'!$E$2:$E$1489,$B$3,'Cleaned Data'!$F$2:$F$1489,$B$4,'Cleaned Data'!$G$2:$G$1489,$B$5,'Cleaned Data'!$O$2:$O$1489,"Delivered",'Cleaned Data'!$C$2:$C$1489,$A45) -> 127 | C45: =SUMIFS('Cleaned Data'!$L$2:$L$1489,'Cleaned Data'!$E$2:$E$1489,$B$3,'Cleaned Data'!$F$2:$F$1489,$B$4,'Cleaned Data'!$G$2:$G$1489,$B$5,'Cleaned Data'!$O$2:$O$1489,"Delivered",'Cleaned Data'!$C$2:$C$1489,$A45) -> 55791 | D45: =IFERROR(C45/B45,0) -> 439.29921
A46: Dec | B46: =COUNTIFS('Cleaned Data'!$E$2:$E$1489,$B$3,'Cleaned Data'!$F$2:$F$1489,$B$4,'Cleaned Data'!$G$2:$G$1489,$B$5,'Cleaned Data'!$O$2:$O$1489,"Delivered",'Cleaned Data'!$C$2:$C$1489,$A46) -> 143 | C46: =SUMIFS('Cleaned Data'!$L$2:$L$1489,'Cleaned Data'!$E$2:$E$1489,$B$3,'Cleaned Data'!$F$2:$F$1489,$B$4,'Cleaned Data'!$G$2:$G$1489,$B$5,'Cleaned Data'!$O$2:$O$1489,"Delivered",'Cleaned Data'!$C$2:$C$1489,$A46) -> 62200 | D46: =IFERROR(C46/B46,0) -> 434.96503
A47: Grand Total | B47: =SUM(B35:B46) -> 1405 | C47: =SUM(C35:C46) -> 625271 | D47: =IFERROR(C47/B47,0) -> 445.03274
A50: PIVOT 4 – Payment Method Analysis
A51: Payment Method | B51: Orders | C51: Net Revenue (₹) | D51: % of Orders
A52: UPI | B52: =COUNTIFS('Cleaned Data'!$E$2:$E$1489,$B$3,'Cleaned Data'!$F$2:$F$1489,$B$4,'Cleaned Data'!$G$2:$G$1489,$B$5,'Cleaned Data'!$O$2:$O$1489,"Delivered",'Cleaned Data'!$H$2:$H$1489,$A52) -> 564 | C52: =SUMIFS('Cleaned Data'!$L$2:$L$1489,'Cleaned Data'!$E$2:$E$1489,$B$3,'Cleaned Data'!$F$2:$F$1489,$B$4,'Cleaned Data'!$G$2:$G$1489,$B$5,'Cleaned Data'!$O$2:$O$1489,"Delivered",'Cleaned Data'!$H$2:$H$1489,$A52) -> 252219 | D52: =IFERROR(B52/SUM(B$52:B$57),0) -> 0.40142349
A53: Credit Card | B53: =COUNTIFS('Cleaned Data'!$E$2:$E$1489,$B$3,'Cleaned Data'!$F$2:$F$1489,$B$4,'Cleaned Data'!$G$2:$G$1489,$B$5,'Cleaned Data'!$O$2:$O$1489,"Delivered",'Cleaned Data'!$H$2:$H$1489,$A53) -> 224 | C53: =SUMIFS('Cleaned Data'!$L$2:$L$1489,'Cleaned Data'!$E$2:$E$1489,$B$3,'Cleaned Data'!$F$2:$F$1489,$B$4,'Cleaned Data'!$G$2:$G$1489,$B$5,'Cleaned Data'!$O$2:$O$1489,"Delivered",'Cleaned Data'!$H$2:$H$1489,$A53) -> 100392 | D53: =IFERROR(B53/SUM(B$52:B$57),0) -> 0.1594306
A54: Debit Card | B54: =COUNTIFS('Cleaned Data'!$E$2:$E$1489,$B$3,'Cleaned Data'!$F$2:$F$1489,$B$4,'Cleaned Data'!$G$2:$G$1489,$B$5,'Cleaned Data'!$O$2:$O$1489,"Delivered",'Cleaned Data'!$H$2:$H$1489,$A54) -> 148 | C54: =SUMIFS('Cleaned Data'!$L$2:$L$1489,'Cleaned Data'!$E$2:$E$1489,$B$3,'Cleaned Data'!$F$2:$F$1489,$B$4,'Cleaned Data'!$G$2:$G$1489,$B$5,'Cleaned Data'!$O$2:$O$1489,"Delivered",'Cleaned Data'!$H$2:$H$1489,$A54) -> 64282 | D54: =IFERROR(B54/SUM(B$52:B$57),0) -> 0.10533808
A55: Cash on Delivery | B55: =COUNTIFS('Cleaned Data'!$E$2:$E$1489,$B$3,'Cleaned Data'!$F$2:$F$1489,$B$4,'Cleaned Data'!$G$2:$G$1489,$B$5,'Cleaned Data'!$O$2:$O$1489,"Delivered",'Cleaned Data'!$H$2:$H$1489,$A55) -> 273 | C55: =SUMIFS('Cleaned Data'!$L$2:$L$1489,'Cleaned Data'!$E$2:$E$1489,$B$3,'Cleaned Data'!$F$2:$F$1489,$B$4,'Cleaned Data'!$G$2:$G$1489,$B$5,'Cleaned Data'!$O$2:$O$1489,"Delivered",'Cleaned Data'!$H$2:$H$1489,$A55) -> 121877 | D55: =IFERROR(B55/SUM(B$52:B$57),0) -> 0.19430605
A56: Wallet | B56: =COUNTIFS('Cleaned Data'!$E$2:$E$1489,$B$3,'Cleaned Data'!$F$2:$F$1489,$B$4,'Cleaned Data'!$G$2:$G$1489,$B$5,'Cleaned Data'!$O$2:$O$1489,"Delivered",'Cleaned Data'!$H$2:$H$1489,$A56) -> 178 | C56: =SUMIFS('Cleaned Data'!$L$2:$L$1489,'Cleaned Data'!$E$2:$E$1489,$B$3,'Cleaned Data'!$F$2:$F$1489,$B$4,'Cleaned Data'!$G$2:$G$1489,$B$5,'Cleaned Data'!$O$2:$O$1489,"Delivered",'Cleaned Data'!$H$2:$H$1489,$A56) -> 78624 | D56: =IFERROR(B56/SUM(B$52:B$57),0) -> 0.12669039
A57: Unknown | B57: =COUNTIFS('Cleaned Data'!$E$2:$E$1489,$B$3,'Cleaned Data'!$F$2:$F$1489,$B$4,'Cleaned Data'!$G$2:$G$1489,$B$5,'Cleaned Data'!$O$2:$O$1489,"Delivered",'Cleaned Data'!$H$2:$H$1489,$A57) -> 18 | C57: =SUMIFS('Cleaned Data'!$L$2:$L$1489,'Cleaned Data'!$E$2:$E$1489,$B$3,'Cleaned Data'!$F$2:$F$1489,$B$4,'Cleaned Data'!$G$2:$G$1489,$B$5,'Cleaned Data'!$O$2:$O$1489,"Delivered",'Cleaned Data'!$H$2:$H$1489,$A57) -> 7877 | D57: =IFERROR(B57/SUM(B$52:B$57),0) -> 0.012811388
A58: Grand Total | B58: =SUM(B52:B57) -> 1405 | C58: =SUM(C52:C57) -> 625271 | D58: =SUM(D52:D57) -> 1
A61: PIVOT 5 – Orders by Weekday
A62: Weekday | B62: Orders | C62: Net Revenue (₹) | D62: Avg Order Value (₹)
A63: Mon | B63: =COUNTIFS('Cleaned Data'!$E$2:$E$1489,$B$3,'Cleaned Data'!$F$2:$F$1489,$B$4,'Cleaned Data'!$G$2:$G$1489,$B$5,'Cleaned Data'!$O$2:$O$1489,"Delivered",'Cleaned Data'!$D$2:$D$1489,$A63) -> 163 | C63: =SUMIFS('Cleaned Data'!$L$2:$L$1489,'Cleaned Data'!$E$2:$E$1489,$B$3,'Cleaned Data'!$F$2:$F$1489,$B$4,'Cleaned Data'!$G$2:$G$1489,$B$5,'Cleaned Data'!$O$2:$O$1489,"Delivered",'Cleaned Data'!$D$2:$D$1489,$A63) -> 72345 | D63: =IFERROR(C63/B63,0) -> 443.83436
A64: Tue | B64: =COUNTIFS('Cleaned Data'!$E$2:$E$1489,$B$3,'Cleaned Data'!$F$2:$F$1489,$B$4,'Cleaned Data'!$G$2:$G$1489,$B$5,'Cleaned Data'!$O$2:$O$1489,"Delivered",'Cleaned Data'!$D$2:$D$1489,$A64) -> 183 | C64: =SUMIFS('Cleaned Data'!$L$2:$L$1489,'Cleaned Data'!$E$2:$E$1489,$B$3,'Cleaned Data'!$F$2:$F$1489,$B$4,'Cleaned Data'!$G$2:$G$1489,$B$5,'Cleaned Data'!$O$2:$O$1489,"Delivered",'Cleaned Data'!$D$2:$D$1489,$A64) -> 83125 | D64: =IFERROR(C64/B64,0) -> 454.23497
A65: Wed | B65: =COUNTIFS('Cleaned Data'!$E$2:$E$1489,$B$3,'Cleaned Data'!$F$2:$F$1489,$B$4,'Cleaned Data'!$G$2:$G$1489,$B$5,'Cleaned Data'!$O$2:$O$1489,"Delivered",'Cleaned Data'!$D$2:$D$1489,$A65) -> 180 | C65: =SUMIFS('Cleaned Data'!$L$2:$L$1489,'Cleaned Data'!$E$2:$E$1489,$B$3,'Cleaned Data'!$F$2:$F$1489,$B$4,'Cleaned Data'!$G$2:$G$1489,$B$5,'Cleaned Data'!$O$2:$O$1489,"Delivered",'Cleaned Data'!$D$2:$D$1489,$A65) -> 80862 | D65: =IFERROR(C65/B65,0) -> 449.23333
A66: Thu | B66: =COUNTIFS('Cleaned Data'!$E$2:$E$1489,$B$3,'Cleaned Data'!$F$2:$F$1489,$B$4,'Cleaned Data'!$G$2:$G$1489,$B$5,'Cleaned Data'!$O$2:$O$1489,"Delivered",'Cleaned Data'!$D$2:$D$1489,$A66) -> 207 | C66: =SUMIFS('Cleaned Data'!$L$2:$L$1489,'Cleaned Data'!$E$2:$E$1489,$B$3,'Cleaned Data'!$F$2:$F$1489,$B$4,'Cleaned Data'!$G$2:$G$1489,$B$5,'Cleaned Data'!$O$2:$O$1489,"Delivered",'Cleaned Data'!$D$2:$D$1489,$A66) -> 91871 | D66: =IFERROR(C66/B66,0) -> 443.82126
A67: Fri | B67: =COUNTIFS('Cleaned Data'!$E$2:$E$1489,$B$3,'Cleaned Data'!$F$2:$F$1489,$B$4,'Cleaned Data'!$G$2:$G$1489,$B$5,'Cleaned Data'!$O$2:$O$1489,"Delivered",'Cleaned Data'!$D$2:$D$1489,$A67) -> 236 | C67: =SUMIFS('Cleaned Data'!$L$2:$L$1489,'Cleaned Data'!$E$2:$E$1489,$B$3,'Cleaned Data'!$F$2:$F$1489,$B$4,'Cleaned Data'!$G$2:$G$1489,$B$5,'Cleaned Data'!$O$2:$O$1489,"Delivered",'Cleaned Data'!$D$2:$D$1489,$A67) -> 103593 | D67: =IFERROR(C67/B67,0) -> 438.95339
A68: Sat | B68: =COUNTIFS('Cleaned Data'!$E$2:$E$1489,$B$3,'Cleaned Data'!$F$2:$F$1489,$B$4,'Cleaned Data'!$G$2:$G$1489,$B$5,'Cleaned Data'!$O$2:$O$1489,"Delivered",'Cleaned Data'!$D$2:$D$1489,$A68) -> 228 | C68: =SUMIFS('Cleaned Data'!$L$2:$L$1489,'Cleaned Data'!$E$2:$E$1489,$B$3,'Cleaned Data'!$F$2:$F$1489,$B$4,'Cleaned Data'!$G$2:$G$1489,$B$5,'Cleaned Data'!$O$2:$O$1489,"Delivered",'Cleaned Data'!$D$2:$D$1489,$A68) -> 102043 | D68: =IFERROR(C68/B68,0) -> 447.55702
A69: Sun | B69: =COUNTIFS('Cleaned Data'!$E$2:$E$1489,$B$3,'Cleaned Data'!$F$2:$F$1489,$B$4,'Cleaned Data'!$G$2:$G$1489,$B$5,'Cleaned Data'!$O$2:$O$1489,"Delivered",'Cleaned Data'!$D$2:$D$1489,$A69) -> 208 | C69: =SUMIFS('Cleaned Data'!$L$2:$L$1489,'Cleaned Data'!$E$2:$E$1489,$B$3,'Cleaned Data'!$F$2:$F$1489,$B$4,'Cleaned Data'!$G$2:$G$1489,$B$5,'Cleaned Data'!$O$2:$O$1489,"Delivered",'Cleaned Data'!$D$2:$D$1489,$A69) -> 91432 | D69: =IFERROR(C69/B69,0) -> 439.57692
A70: Grand Total | B70: =SUM(B63:B69) -> 1405 | C70: =SUM(C63:C69) -> 625271 | D70: =IFERROR(C70/B70,0) -> 445.03274
A73: PIVOT 6 – Cancellation Analysis by City
A74: City | B74: Orders Placed | C74: Cancelled | D74: Cancellation Rate
A75: Mumbai | B75: =COUNTIFS('Cleaned Data'!$E$2:$E$1489,$B$3,'Cleaned Data'!$F$2:$F$1489,$B$4,'Cleaned Data'!$G$2:$G$1489,$B$5,'Cleaned Data'!$E$2:$E$1489,$A75) -> 294 | C75: =COUNTIFS('Cleaned Data'!$E$2:$E$1489,$B$3,'Cleaned Data'!$F$2:$F$1489,$B$4,'Cleaned Data'!$G$2:$G$1489,$B$5,'Cleaned Data'!$O$2:$O$1489,"Cancelled",'Cleaned Data'!$E$2:$E$1489,$A75) -> 18 | D75: =IFERROR(C75/B75,0) -> 0.06122449
A76: Delhi | B76: =COUNTIFS('Cleaned Data'!$E$2:$E$1489,$B$3,'Cleaned Data'!$F$2:$F$1489,$B$4,'Cleaned Data'!$G$2:$G$1489,$B$5,'Cleaned Data'!$E$2:$E$1489,$A76) -> 301 | C76: =COUNTIFS('Cleaned Data'!$E$2:$E$1489,$B$3,'Cleaned Data'!$F$2:$F$1489,$B$4,'Cleaned Data'!$G$2:$G$1489,$B$5,'Cleaned Data'!$O$2:$O$1489,"Cancelled",'Cleaned Data'!$E$2:$E$1489,$A76) -> 21 | D76: =IFERROR(C76/B76,0) -> 0.069767442
A77: Bengaluru | B77: =COUNTIFS('Cleaned Data'!$E$2:$E$1489,$B$3,'Cleaned Data'!$F$2:$F$1489,$B$4,'Cleaned Data'!$G$2:$G$1489,$B$5,'Cleaned Data'!$E$2:$E$1489,$A77) -> 343 | C77: =COUNTIFS('Cleaned Data'!$E$2:$E$1489,$B$3,'Cleaned Data'!$F$2:$F$1489,$B$4,'Cleaned Data'!$G$2:$G$1489,$B$5,'Cleaned Data'!$O$2:$O$1489,"Cancelled",'Cleaned Data'!$E$2:$E$1489,$A77) -> 24 | D77: =IFERROR(C77/B77,0) -> 0.069970845
A78: Hyderabad | B78: =COUNTIFS('Cleaned Data'!$E$2:$E$1489,$B$3,'Cleaned Data'!$F$2:$F$1489,$B$4,'Cleaned Data'!$G$2:$G$1489,$B$5,'Cleaned Data'!$E$2:$E$1489,$A78) -> 193 | C78: =COUNTIFS('Cleaned Data'!$E$2:$E$1489,$B$3,'Cleaned Data'!$F$2:$F$1489,$B$4,'Cleaned Data'!$G$2:$G$1489,$B$5,'Cleaned Data'!$O$2:$O$1489,"Cancelled",'Cleaned Data'!$E$2:$E$1489,$A78) -> 8 | D78: =IFERROR(C78/B78,0) -> 0.041450777
A79: Chennai | B79: =COUNTIFS('Cleaned Data'!$E$2:$E$1489,$B$3,'Cleaned Data'!$F$2:$F$1489,$B$4,'Cleaned Data'!$G$2:$G$1489,$B$5,'Cleaned Data'!$E$2:$E$1489,$A79) -> 115 | C79: =COUNTIFS('Cleaned Data'!$E$2:$E$1489,$B$3,'Cleaned Data'!$F$2:$F$1489,$B$4,'Cleaned Data'!$G$2:$G$1489,$B$5,'Cleaned Data'!$O$2:$O$1489,"Cancelled",'Cleaned Data'!$E$2:$E$1489,$A79) -> 6 | D79: =IFERROR(C79/B79,0) -> 0.052173913
A80: Pune | B80: =COUNTIFS('Cleaned Data'!$E$2:$E$1489,$B$3,'Cleaned Data'!$F$2:$F$1489,$B$4,'Cleaned Data'!$G$2:$G$1489,$B$5,'Cleaned Data'!$E$2:$E$1489,$A80) -> 105 | C80: =COUNTIFS('Cleaned Data'!$E$2:$E$1489,$B$3,'Cleaned Data'!$F$2:$F$1489,$B$4,'Cleaned Data'!$G$2:$G$1489,$B$5,'Cleaned Data'!$O$2:$O$1489,"Cancelled",'Cleaned Data'!$E$2:$E$1489,$A80) -> 2 | D80: =IFERROR(C80/B80,0) -> 0.019047619
A81: Kolkata | B81: =COUNTIFS('Cleaned Data'!$E$2:$E$1489,$B$3,'Cleaned Data'!$F$2:$F$1489,$B$4,'Cleaned Data'!$G$2:$G$1489,$B$5,'Cleaned Data'!$E$2:$E$1489,$A81) -> 76 | C81: =COUNTIFS('Cleaned Data'!$E$2:$E$1489,$B$3,'Cleaned Data'!$F$2:$F$1489,$B$4,'Cleaned Data'!$G$2:$G$1489,$B$5,'Cleaned Data'!$O$2:$O$1489,"Cancelled",'Cleaned Data'!$E$2:$E$1489,$A81) -> 1 | D81: =IFERROR(C81/B81,0) -> 0.013157895
A82: Ahmedabad | B82: =COUNTIFS('Cleaned Data'!$E$2:$E$1489,$B$3,'Cleaned Data'!$F$2:$F$1489,$B$4,'Cleaned Data'!$G$2:$G$1489,$B$5,'Cleaned Data'!$E$2:$E$1489,$A82) -> 61 | C82: =COUNTIFS('Cleaned Data'!$E$2:$E$1489,$B$3,'Cleaned Data'!$F$2:$F$1489,$B$4,'Cleaned Data'!$G$2:$G$1489,$B$5,'Cleaned Data'!$O$2:$O$1489,"Cancelled",'Cleaned Data'!$E$2:$E$1489,$A82) -> 3 | D82: =IFERROR(C82/B82,0) -> 0.049180328
A83: Grand Total | B83: =SUM(B75:B82) -> 1488 | C83: =SUM(C75:C82) -> 83 | D83: =IFERROR(C83/B83,0) -> 0.05577957
A86: PIVOT 7 – New vs Returning Customers
A87: Customer Type | B87: Orders | C87: Net Revenue (₹) | D87: Avg Order Value (₹)
A88: New | B88: =COUNTIFS('Cleaned Data'!$E$2:$E$1489,$B$3,'Cleaned Data'!$F$2:$F$1489,$B$4,'Cleaned Data'!$G$2:$G$1489,$B$5,'Cleaned Data'!$O$2:$O$1489,"Delivered",'Cleaned Data'!$G$2:$G$1489,$A88) -> 532 | C88: =SUMIFS('Cleaned Data'!$L$2:$L$1489,'Cleaned Data'!$E$2:$E$1489,$B$3,'Cleaned Data'!$F$2:$F$1489,$B$4,'Cleaned Data'!$G$2:$G$1489,$B$5,'Cleaned Data'!$O$2:$O$1489,"Delivered",'Cleaned Data'!$G$2:$G$1489,$A88) -> 226454 | D88: =IFERROR(C88/B88,0) -> 425.66541
A89: Returning | B89: =COUNTIFS('Cleaned Data'!$E$2:$E$1489,$B$3,'Cleaned Data'!$F$2:$F$1489,$B$4,'Cleaned Data'!$G$2:$G$1489,$B$5,'Cleaned Data'!$O$2:$O$1489,"Delivered",'Cleaned Data'!$G$2:$G$1489,$A89) -> 873 | C89: =SUMIFS('Cleaned Data'!$L$2:$L$1489,'Cleaned Data'!$E$2:$E$1489,$B$3,'Cleaned Data'!$F$2:$F$1489,$B$4,'Cleaned Data'!$G$2:$G$1489,$B$5,'Cleaned Data'!$O$2:$O$1489,"Delivered",'Cleaned Data'!$G$2:$G$1489,$A89) -> 398817 | D89: =IFERROR(C89/B89,0) -> 456.83505
A90: Grand Total | B90: =SUM(B88:B89) -> 1405 | C90: =SUM(C88:C89) -> 625271 | D90: =IFERROR(C90/B90,0) -> 445.03274

Sheet Charts
A1: CHARTS (linked to Pivot Tables – change Dashboard filters to update)

Sheet Dashboard
B1: 🍔 FOOD DELIVERY SALES DASHBOARD – 2025
B3: FILTERS (select from dropdowns)
B4: City | C4: All | E4: ◀ Pick a City / Cuisine / Customer Type – every KPI and chart updates instantly.
B5: Cuisine | C5: All | E5: Set all three back to 'All' to see the full year.
B6: Customer Type | C6: All
B8: NET REVENUE | D8: DELIVERED ORDERS | F8: AVG ORDER VALUE | H8: AVG DELIVERY TIME | J8: AVG RATING | L8: CANCELLATION RATE
B9: =SUMIFS('Cleaned Data'!$L$2:$L$1489,'Cleaned Data'!$E$2:$E$1489,'Pivot Tables'!$B$3,'Cleaned Data'!$F$2:$F$1489,'Pivot Tables'!$B$4,'Cleaned Data'!$G$2:$G$1489,'Pivot Tables'!$B$5) -> 625271 | D9: =COUNTIFS('Cleaned Data'!$E$2:$E$1489,'Pivot Tables'!$B$3,'Cleaned Data'!$F$2:$F$1489,'Pivot Tables'!$B$4,'Cleaned Data'!$G$2:$G$1489,'Pivot Tables'!$B$5,'Cleaned Data'!$O$2:$O$1489,"Delivered") -> 1405 | F9: =IFERROR(B9/D9,0) -> 445.03274 | H9: =IFERROR(AVERAGEIFS('Cleaned Data'!$M$2:$M$1489,'Cleaned Data'!$E$2:$E$1489,'Pivot Tables'!$B$3,'Cleaned Data'!$F$2:$F$1489,'Pivot Tables'!$B$4,'Cleaned Data'!$G$2:$G$1489,'Pivot Tables'!$B$5,'Cleaned Data'!$O$2:$O$1489,"Delivered"),0) -> 36.120996 | J9: =IFERROR(AVERAGEIFS('Cleaned Data'!$N$2:$N$1489,'Cleaned Data'!$E$2:$E$1489,'Pivot Tables'!$B$3,'Cleaned Data'!$F$2:$F$1489,'Pivot Tables'!$B$4,'Cleaned Data'!$G$2:$G$1489,'Pivot Tables'!$B$5,'Cleaned Data'!$O$2:$O$1489,"Delivered"),0) -> 4.2583271 | L9: =IFERROR(COUNTIFS('Cleaned Data'!$E$2:$E$1489,'Pivot Tables'!$B$3,'Cleaned Data'!$F$2:$F$1489,'Pivot Tables'!$B$4,'Cleaned Data'!$G$2:$G$1489,'Pivot Tables'!$B$5,'Cleaned Data'!$O$2:$O$1489,"Cancelled")/COUNTIFS('Cleaned Data'!$E$2:$E$1489,'Pivot Tables'!$B$3,'Cleaned Data'!$F$2:$F$1489,'Pivot Tables'!$B$4,'Cleaned Data'!$G$2:$G$1489,'Pivot Tables'!$B$5),0) -> 0.05577957
B63: Source: Cleaned Data (tblOrders) via Pivot Tables sheet. Dataset: simulated Indian food-delivery orders, Jan–Dec 2025.

Sheet Insights
A1: KEY INSIGHTS & OBSERVATIONS
A2: Figures below are for the full year with all filters = 'All'.
A4: 1 | B4: Revenue concentration: Bengaluru, Delhi and Mumbai together generate 63% of total net revenue (₹625,271); Bengaluru leads with ₹141,596.
A5: 2 | B5: Cuisine mix: North Indian is the top revenue cuisine (22% share), followed by Pizza (18%); Desserts contributes the least (4%).
A6: 3 | B6: Seasonality / growth: monthly revenue grew from ₹43,004 in Jan to a peak of ₹62,200 in Dec (lowest: Apr, ₹39,431), showing an overall upward demand trend through the year.
A7: 4 | B7: Weekend effect: Fri–Sun account for 48% of delivered orders although they are only 43% of days – a clear weekend demand spike worth staffing and promoting for.
A8: 5 | B8: Payments: UPI is the most used method (40% of orders), then Cash on Delivery (19%); Cash on Delivery still holds a notable share, adding cash-handling cost.
A9: 6 | B9: Delivery speed vs satisfaction: avg rating is 4.49 for ≤30 min deliveries, 4.24 for 31–45 min and 3.87 for >45 min – slower deliveries clearly lower ratings. Bengaluru is the slowest city (41.9 min avg).
A10: 7 | B10: Cancellations: overall cancellation rate is 5.6%; Bengaluru is highest at 7.0%, lowest in Kolkata (1.3%) – cities with longer delivery times tend to see more cancellations.
A11: 8 | B11: Customer type: Returning customers make up 62% of delivered orders with avg net order value ₹457 vs ₹426 for new customers (new customers receive heavier discounts).
A13: RECOMMENDATIONS
A14: ➜ | B14: Add riders / dark-kitchen capacity in the slowest cities to bring delivery time under 35 minutes.
A15: ➜ | B15: Run weekend-specific bundles for top cuisines (e.g., Biryani, Pizza) and weekday lunch offers to even out demand.
A16: ➜ | B16: Push UPI cashback and reduce COD share to cut cash-handling costs and cancellations.
A17: ➜ | B17: Convert new customers with first-order discounts but protect margin using minimum-order thresholds.
A19: DATA CLEANING LOG
A20: • | B20: Raw records: 1525 → Cleaned records: 1488
A21: • | B21: Removed 25 duplicate Order_IDs
A22: • | B22: Removed 12 rows with missing Order_Value
A23: • | B23: Filled 18 missing Payment_Method values with 'Unknown'
A24: • | B24: Standardised City names (trim/case; 'Bangalore' → 'Bengaluru') and Customer_Type case
A25: • | B25: Converted text dates (dd-mm-yyyy) to real Excel dates
A26: • | B26: Added Month, Weekday and Net_Revenue (=Order_Value − Discount + Delivery_Fee, 0 if cancelled) as formulas
A27: • | B27: Converted range into Excel Table 'tblOrders'
A28: • | B28: Dataset note: simulated Indian food-delivery data (1,500 orders, 2025). Swap in a Kaggle dataset by pasting into Cleaned Data table.
